Workbook

Sheet Notes
A1: 46097 | B1: INcludes additional information regarding business recall date / annoucnement date (am using businesse recall date for now) | C1: CA
A2: 46097 | B2: Product Type would have to be fully captured again | C2: CA
A3: 46097 | B3: Adulterated: Prohibited Product | C3: CA
A4: 46097 | B4: The new style of categorized pesticides hides the practices from consumers, and which pesticides they may have been exposed to | C4: CA
A5: 46097 | B5: for connectedcannabis co _ why are there two different companies listed as the legal business name? which is correct? All point to same business website (https://recalls.cannabis.ca.gov/recalls/6761f90394a546fcd1a8843a, https://recalls.cannabis.ca.gov/recalls/6761c1de449a15805975db10) | C5: CA
A6: 46097 | B6: What is 'invalid batch testing' (see 'Canna America Live Resin Integrated Vaporizer')
A7: 46097 | B7: Lab isn't listed on recall notcied (note the amount of recalls around 2/205 like https://docs.google.com/spreadsheets/d/10YkN4Rqg58UGLMEH5R_pS1_9uNAoTdNG2UDLxc21FXs/edit?gid=665012503#gid=665012503 being recalled for incomplete testing due to no solvent testing
A8: 46097 | B8: Why different business names for Tonik Beverages? (go NXT LVL vs. baked betty's)
A9: 46097 | B9: So interesting that not one of the Oakfruitland (OFL) Pre-Roll had dates on the packaging! Wildf!
A10: 46097 | B10: Why was the Honey Edible recall given over a month betrween business recall and pub date? (https://recalls.cannabis.ca.gov/recalls/67f44320ef33cec4b8c75618)
A11: 46097 | B11: Weird no dates for ( smartweed flower)
A12: 46097 | B12: Adulterated: other is far too large, and isn't allowing CA good granularity Includes distributor without distributor license, no GMP, etc.
A13: 46098 | B13: Many of CO's Health Advisories do not contain information about the product
A14: 46098 | B14: https://drive.google.com/file/d/1_wFzm3GOJfzE6tmSqIhIcyvtI8ocZJDf/view - this case has batches that had Total Yeast and Mold but also identified other batches that were in teh same space as the contaminants
A15: 46098 | B15: Assuming 'elemental impurities' in the CO dataset indicate heavy metals
A16: 46098 | B16: CO Expansion: Includes a new pesticde :https://drive.google.com/file/d/155K5itnbbcG9r6nxemU_8UHDu709cMJB/view
A17: 46098 | B17: Why so amny actions in CO on 1/22
... A41: 46302 | B41: Is oregon just not doing recalls anymore, or have they stumbled into the safest product ever combined with their new lab?

Sheet State OV
A1: State | B1: Data | C1: Recall Page Link | D1: Recall Page Link | E1: Update Date | F1: notes
A2: Alabama | E2: 46296
A3: Alaska | B3: No | C3: https://www.commerce.alaska.gov/web/amco/ | E3: 46296 | F3: It's not only for recalls, so it doesn't count
A4: Arizona | B4: Yes | C4: https://www.azdhs.gov/preparedness/epidemiology-disease-control/food-safety-environmental-services/index.php#marijuana-kitchen-product-recalls | E4: 46296 | F4: Also need to check announcements
A5: Arkansas | B5: No | E5: 46296 | F5: No centralized place to record recalls, It's expected the dispensaries do so. No way to trace or understand supply chain safety issues. Boo.
A6: California | B6: Yes | C6: https://www.cannabis.ca.gov/consumers/cannabis-recalls-and-safety-notices/ | E6: 46296 | F6: Extensive Now
A7: Colorado | B7: Yes | C7: https://sbg.colorado.gov/med/health-and-safety-advisories | E7: 46297 | F7: press releases; not recalls, health advisories
A8: Connecticut | B8: No | C8: No Centralized Page found, but recalls evident | E8: 46297
A9: Delaware | B9: No | E9: 46297
A10: Florida | B10: No | E10: 46297
A11: Georgia | B11: No | E11: 46297
A12: Hawaii | B12: No | E12: 46297
A13: Idaho | E13: 46297
A14: Illinois | B14: No | C14: https://idfpr.illinois.gov/profs/cannabis.html | E14: 46297
A15: Indiana | E15: 46297
A16: Iowa | E16: 46297
A17: Kansas | E17: 46297
A18: Kentucky | B18: No | E18: 46297
A19: Louisiana | B19: No | E19: 46297
A20: Maine | B20: No | C20: https://www.maine.gov/dafs/ocp/resources/recalls | E20: 46297
A21: Maryland | B21: No | C21: https://cannabis.maryland.gov/pages/bulletins.aspx | E21: 46297
A22: Massachusetts | B22: No | C22: https://masscannabiscontrol.com/news/public-health-and-safety-advisories/ | E22: 46298
A23: Michigan | B23: Yes | C23: https://www.michigan.gov/cra/bulletins | E23: 46298
A24: Minnesota | B24: No | C24: https://mn.gov/ocm/businesses/recalls.jsp | E24: 46298 | F24: ...only hemp recalls? Really?
A25: Mississippi | B25: No | C25: https://www.mmcp.ms.gov/patient-purchased-recall-items | E25: 46298
A26: Missouri | B26: No | C26: https://health.mo.gov/business-professionals/cannabis-regulation/licensee-compliance-and-guidance/product-recalls | E26: 46299
A27: Montana | B27: Yes | C27: https://revenue.mt.gov/card/cannabis/cannabis-product-recalls | E27: 46300 | F27: but have no recalls yet
A28: Nebraska | E28: 46301
A29: Nevada | B29: Yes | C29: https://ccb.nv.gov/guidance/#item-1 | E29: 46302
A30: New Hampshire | B30: No | E30: 46302
A31: New Jersey | B31: Yes | C31: https://www.nj.gov/cannabis/adult-personal/recalls/ | E31: 46303 | F31: None listed; some in press
A32: New Mexico | B32: Yes | C32: https://www.rld.nm.gov/cannabis/data-news/cannabis-recalls/ | E32: 46304
A33: New York | B33: No | C33: https://cannabis.ny.gov/recalls | D33: New | E33: 46305 | F33: It says they will be posted on that page but the unregulated hemp products they recalled aren't included.
A34: North Dakota | B34: No | E34: 46306
A35: Ohio | B35: Yes | C35: https://com.ohio.gov/divisions-and-programs/cannabis-control/product-safety | E35: 46306 | F35: One from December not included
A36: Oklahoma | B36: Yes | C36: https://oklahoma.gov/omma/recalls/embargoed-and-recalled-products.html | E36: 46306
A37: Oregon | B37: Yes | C37: https://www.oregon.gov/olcc/Pages/product-recalls.aspx | E37: 46306
A38: Pennsylvania | B38: No | E38: 46306
A39: Rhode Island | B39: No | E39: 46306
A40: South Carolina | E40: 46306
A41: South Dakota | B41: No | E41: 46306
A42: Tennessee | E42: 46306
A43: Texas | E43: 46306
A44: Utah | E44: 46306
A45: Vermont | B45: No | E45: 46306
A46: Virginia | E46: 46306
A47: Washington | B47: Yes | C47: https://lcb.wa.gov/examiners/recalls | E47: 46306
A48: West Virginia | B48: No | E48: 46306
A49: Wisconsin | E49: 46306
A50: Wyoming | E50: 46306
A51: District of Columbia | B51: No | E51: 46306

Sheet Recall Analysis
A1: ID | B1: Business Recall Date | C1: Reg Recall Ann | D1: State | E1: Link | F1: Web Archive Link | G1: Type | H1: Product Type | I1: Brand Name / Product Name | J1: Company / Producer | K1: Lab | L1: MSO | M1: Dated? | N1: Harvest or Package Date | O1: Sale Date | P1: Reason | Q1: Source | R1: Category | S1: Tight Category
A2: 43781AlaskaCalm N Collective, LLC | C2: 43781 | D2: Alaska | E2: https://web.archive.org/web/20230619022017/https://www.commerce.alaska.gov/web/Portals/9/pub/MCB/Minutes/2020/01.23/Tab6.pdf#page=7#page=7 | F2: https://web.archive.org/web/20230619022017/https://www.commerce.alaska.gov/web/Portals/9/pub/MCB/Minutes/2020/01.23/Tab6.pdf#page=7#page=7 | G2: Mandatory | H2: Unspecified | I2: Calm N Collective | J2: Calm N Collective, LLC | M2: N | P2: Clonex, Root Pac, Big Time Exterminator, Super Thrive | Q2: State Page | R2: =VLOOKUP(P2,Categorizations!A:C,2,FALSE()) -> Pesticides | S2: =VLOOKUP(P2,Categorizations!A:C,3,FALSE()) -> Pesticides
A3: 44988AlaskaWill’s World Extracts | C3: 44988 | D3: Alaska | E3: https://web.archive.org/web/20250719042132/https://www.commerce.alaska.gov/web/Portals/9/pub/HomePage/Press%20Release/Director%20Advisory.administrativehold.3.2.23.final%20(2).pdf | F3: https://web.archive.org/web/20250719042132/https://www.commerce.alaska.gov/web/Portals/9/pub/HomePage/Press%20Release/Director%20Advisory.administrativehold.3.2.23.final%20(2).pdf | G3: Mandatory | H3: Concentrates | I3: All marijuana concentrates in any form and infused joints manufactured by Will’s World Extracts, | J3: Will’s World Extracts | M3: N | P3: unregistered and unlicensed THC concentrates | Q3: State Recall Page | R3: =VLOOKUP(P3,Categorizations!A:C,2,FALSE()) -> Diverted Product | S3: =VLOOKUP(P3,Categorizations!A:C,3,FALSE()) -> Prohibited Additives / Product
A4: =CONCATENATE(C4,J4) -> 44370Harvest Platinum | C4: 44370 | D4: Arizona | E4: https://web.archive.org/web/20260000000000*/https://www.azdhs.gov/director/public-information-office/index.php#news-release-062321 | F4: https://web.archive.org/web/20260000000000*/https://www.azdhs.gov/director/public-information-office/index.php#news-release-062321 | G4: Voluntary | H4: Flower | I4: Harvest Platinum 14g Pre Pack Indica Flower (Glazed Apricot Gelato) | J4: Harvest Platinum | M4: C | N4: 44292 | P4: Salmonella | Q4: State Recall Page | R4: =VLOOKUP(P4,Categorizations!A:C,2,FALSE()) -> Salmonella | S4: =VLOOKUP(P4,Categorizations!A:C,3,FALSE()) -> Microbial Contamination
A5: 44370Harvest Platinum 2 | C5: 44370 | D5: Arizona | E5: https://www.azdhs.gov/director/public-information-office/index.php#news-release-062321 | G5: Voluntary | H5: Flower | I5: Harvest Platinum 14g Pre Pack Sativa Flower (Tiger Haze) | J5: Harvest Platinum | M5: C | N5: 44292 | P5: Aspergillus | Q5: State Recall Page | R5: =VLOOKUP(P5,Categorizations!A:C,2,FALSE()) -> Aspergillus | S5: =VLOOKUP(P5,Categorizations!A:C,3,FALSE()) -> Microbial Contamination
A6: =CONCATENATE(C6,J6) -> 44370Modern Flower | C6: 44370 | D6: Arizona | E6: https://www.azdhs.gov/director/public-information-office/index.php#news-release-062321 | G6: Voluntary | H6: Flower | I6: Modern Flower 3.5g Pre Pack Indica Flower (Orange Acai) | J6: Modern Flower | M6: C | N6: 44307 | P6: Aspergillus sp. | Q6: State Recall Page | R6: =VLOOKUP(P6,Categorizations!A:C,2,FALSE()) -> Aspergillus | S6: =VLOOKUP(P6,Categorizations!A:C,3,FALSE()) -> Microbial Contamination
A7: =CONCATENATE(C7,J7) -> 44370Sol Flower | C7: 44370 | D7: Arizona | E7: https://www.azdhs.gov/director/public-information-office/index.php#news-release-062321 | G7: Voluntary | H7: Flower | I7: Sol Flower Dispensaries and Establishments Tahiti Lime | J7: Sol Flower | M7: C | N7: 44217 | P7: Aspergillus sp. | Q7: State Recall Page | R7: =VLOOKUP(P7,Categorizations!A:C,2,FALSE()) -> Aspergillus | S7: =VLOOKUP(P7,Categorizations!A:C,3,FALSE()) -> Microbial Contamination
A8: =CONCATENATE(C8,J8) -> 44370EHF | C8: 44370 | D8: Arizona | E8: https://www.azdhs.gov/director/public-information-office/index.php#news-release-062321 | G8: Voluntary | H8: Flower | I8: EHF (Elephant Head Farms) HAT Trick #17 Flower | J8: EHF | M8: C | N8: 44263 | P8: Salmonella | Q8: State Recall Page | R8: =VLOOKUP(P8,Categorizations!A:C,2,FALSE()) -> Salmonella | S8: =VLOOKUP(P8,Categorizations!A:C,3,FALSE()) -> Microbial Contamination
A9: =CONCATENATE(C9,J9) -> 44370Mohave | C9: 44370 | D9: Arizona | E9: https://www.azdhs.gov/director/public-information-office/index.php#news-release-062321 | G9: Voluntary | H9: Pre-Roll | I9: Mohave Cannabis Preroll | J9: Mohave | M9: N | P9: Salmonella | Q9: State Recall Page | R9: =VLOOKUP(P9,Categorizations!A:C,2,FALSE()) -> Salmonella | S9: =VLOOKUP(P9,Categorizations!A:C,3,FALSE()) -> Microbial Contamination
A10: =CONCATENATE(C10,J10) -> 44370Tru Infusion | C10: 44370 | D10: Arizona | E10: https://www.azdhs.gov/director/public-information-office/index.php#news-release-062321 | G10: Voluntary | H10: Flower | I10: Tru Infusion Flower Caked Up Cherries | J10: Tru Infusion | M10: C | N10: 44281 | P10: Aspergillus sp. | Q10: State Recall Page | R10: =VLOOKUP(P10,Categorizations!A:C,2,FALSE()) -> Aspergillus | S10: =VLOOKUP(P10,Categorizations!A:C,3,FALSE()) -> Microbial Contamination
A11: =CONCATENATE(C11,J11) -> 44370Pharm Chemistry | C11: 44370 | D11: Arizona | E11: https://www.azdhs.gov/director/public-information-office/index.php#news-release-062321 | G11: Voluntary | H11: Flower, Pre-Roll | I11: The Pharm Chemistry #1 (HD 3/24/21) | J11: Pharm Chemistry | M11: N | P11: Aspergillus sp. | Q11: State Recall Page | R11: =VLOOKUP(P11,Categorizations!A:C,2,FALSE()) -> Aspergillus | S11: =VLOOKUP(P11,Categorizations!A:C,3,FALSE()) -> Microbial Contamination
A12: 44511ArizonaBaked Bros / Toasted | C12: 44511 | D12: Arizona | E12: https://www.azdhs.gov/director/public-information-office/index.php#news-release-111121 | G12: Voluntary | H12: Flower | I12: Baked Bros | J12: Baked Bros | M12: N | P12: Salmonella | Q12: State Recall Page | R12: =VLOOKUP(P12,Categorizations!A:C,2,FALSE()) -> Salmonella | S12: =VLOOKUP(P12,Categorizations!A:C,3,FALSE()) -> Microbial Contamination
A13: 44511ArizonaToasted | C13: 44511 | D13: Arizona | E13: https://www.azdhs.gov/director/public-information-office/index.php#news-release-111121 | G13: Voluntary | H13: Distillate | I13: Toasted | J13: Toasted | M13: N | P13: Aspergillus sp. | Q13: State Recall Page | R13: =VLOOKUP(P13,Categorizations!A:C,2,FALSE()) -> Aspergillus | S13: =VLOOKUP(P13,Categorizations!A:C,3,FALSE()) -> Microbial Contamination
A14: 44875ArizonaPP Wellness | C14: 44875 | D14: Arizona | E14: https://www.azdhs.gov/director/public-information-office/index.php#news-release-111022 | G14: Voluntary | H14: Flower | I14: PP Wellness El Alquimista | J14: PP Wellness | M14: N | P14: Aspergillus sp. | Q14: State Recall Page | R14: =VLOOKUP(P14,Categorizations!A:C,2,FALSE()) -> Aspergillus | S14: =VLOOKUP(P14,Categorizations!A:C,3,FALSE()) -> Microbial Contamination
A15: 44875ArizonaPP Wellness2 | C15: 44875 | D15: Arizona | E15: https://www.azdhs.gov/director/public-information-office/index.php#news-release-111022 | G15: Voluntary | H15: Flower | I15: PP Wellness Tangie Head | J15: PP Wellness | M15: N | P15: Aspergillus sp. | Q15: State Recall Page | R15: =VLOOKUP(P15,Categorizations!A:C,2,FALSE()) -> Aspergillus | S15: =VLOOKUP(P15,Categorizations!A:C,3,FALSE()) -> Microbial Contamination
A16: 44875ArizonaPP Wellness3 | C16: 44875 | D16: Arizona | E16: https://www.azdhs.gov/director/public-information-office/index.php#news-release-111022 | G16: Voluntary | H16: Flower | I16: PP Wellness Nasty Girl | J16: PP Wellness | M16: N | P16: Aspergillus sp. | Q16: State Recall Page | R16: =VLOOKUP(P16,Categorizations!A:C,2,FALSE()) -> Aspergillus | S16: =VLOOKUP(P16,Categorizations!A:C,3,FALSE()) -> Microbial Contamination
A17: 44875ArizonaPP Wellness4 | C17: 44875 | D17: Arizona | E17: https://www.azdhs.gov/director/public-information-office/index.php#news-release-111022 | G17: Voluntary | H17: Flower | I17: PP Wellness The Juice | J17: PP Wellness | M17: N | P17: Aspergillus sp. | Q17: State Recall Page | R17: =VLOOKUP(P17,Categorizations!A:C,2,FALSE()) -> Aspergillus | S17: =VLOOKUP(P17,Categorizations!A:C,3,FALSE()) -> Microbial Contamination
A18: 44875ArizonaPP Wellness5 | C18: 44875 | D18: Arizona | E18: https://www.azdhs.gov/director/public-information-office/index.php#news-release-111022 | G18: Voluntary | H18: Flower | I18: PP Wellness Gorilla Grapevine | J18: PP Wellness | M18: N | P18: Aspergillus sp. | Q18: State Recall Page | R18: =VLOOKUP(P18,Categorizations!A:C,2,FALSE()) -> Aspergillus | S18: =VLOOKUP(P18,Categorizations!A:C,3,FALSE()) -> Microbial Contamination
A19: 44875ArizonaPP Wellness6 | C19: 44875 | D19: Arizona | E19: AZDHS | Financial Services | G19: Voluntary | H19: Flower | I19: PP Wellness The Juice | J19: PP Wellness | M19: N | P19: Aspergillus sp. | Q19: State Recall Page | R19: =VLOOKUP(P19,Categorizations!A:C,2,FALSE()) -> Aspergillus | S19: =VLOOKUP(P19,Categorizations!A:C,3,FALSE()) -> Microbial Contamination
A20: =CONCATENATE(C20,D20,J20) -> 45006ArizonaSource One Meds | C20: 45006 | D20: Arizona | E20: https://www.azdhs.gov/policy-intergovernmental-affairs/index.php#news-release-032123 | G20: Voluntary | H20: Flower | I20: Muddy Waters | J20: Source One Meds | M20: N | P20: Aspergillus | Q20: State Recall Page | R20: =VLOOKUP(P20,Categorizations!A:C,2,FALSE()) -> Aspergillus | S20: =VLOOKUP(P20,Categorizations!A:C,3,FALSE()) -> Microbial Contamination
A21: =CONCATENATE(C21,D21,J21) -> 45006ArizonaNature’s Wonder | C21: 45006 | D21: Arizona | E21: https://www.azdhs.gov/director/public-information-office/index.php#news-release-032123 | G21: Voluntary | H21: Flower | I21: Mango Sunrise | J21: Nature’s Wonder | M21: N | P21: Aspergillus | Q21: State Recall Page | R21: =VLOOKUP(P21,Categorizations!A:C,2,FALSE()) -> Aspergillus | S21: =VLOOKUP(P21,Categorizations!A:C,3,FALSE()) -> Microbial Contamination
A22: =CONCATENATE(C22,D22,J22) -> 45006ArizonaPotent Planet | C22: 45006 | D22: Arizona | E22: https://www.azdhs.gov/director/public-information-office/index.php#news-release-032123 | G22: Voluntary | H22: Flower | I22: Blood Oath | J22: Potent Planet | M22: N | P22: Aspergillus | Q22: State Recall Page | R22: =VLOOKUP(P22,Categorizations!A:C,2,FALSE()) -> Aspergillus | S22: =VLOOKUP(P22,Categorizations!A:C,3,FALSE()) -> Microbial Contamination
A23: =CONCATENATE(C23,D23,J23) -> 45006ArizonaDeep Root pHarm | C23: 45006 | D23: Arizona | E23: https://www.azdhs.gov/director/public-information-office/index.php#news-release-032123 | G23: Voluntary | H23: Flower | I23: Jenny Kush | J23: Deep Root pHarm | M23: N | P23: Aspergillus | Q23: State Recall Page | R23: =VLOOKUP(P23,Categorizations!A:C,2,FALSE()) -> Aspergillus | S23: =VLOOKUP(P23,Categorizations!A:C,3,FALSE()) -> Microbial Contamination
A24: =CONCATENATE(C24,D24,J24,2) -> 45006ArizonaDeep Root pHarm2 | C24: 45006 | D24: Arizona | E24: https://www.azdhs.gov/director/public-information-office/index.php#news-release-032123 | G24: Voluntary | H24: Flower | I24: Big Mac | J24: Deep Root pHarm | M24: N | P24: Aspergillus | Q24: State Recall Page | R24: =VLOOKUP(P24,Categorizations!A:C,2,FALSE()) -> Aspergillus | S24: =VLOOKUP(P24,Categorizations!A:C,3,FALSE()) -> Microbial Contamination
A25: 45079ArizonaTruinfusion | C25: 45079 | D25: Arizona | E25: https://www.azdhs.gov/policy-intergovernmental-affairs/index.php#news-release-060223 | G25: Voluntary | H25: Flower | I25: Truinfusion Zombie Cookies | J25: Truinfusion | M25: N | P25: Aspergillus | Q25: State Page | R25: =VLOOKUP(P25,Categorizations!A:C,2,FALSE()) -> Aspergillus | S25: =VLOOKUP(P25,Categorizations!A:C,3,FALSE()) -> Microbial Contamination
A26: 45079ArizonaTruinfusion2 | C26: 45079 | D26: Arizona | E26: https://www.azdhs.gov/policy-intergovernmental-affairs/index.php#news-release-060223 | G26: Voluntary | H26: Flower | I26: Truinfusion Peach Gas | J26: Truinfusion | M26: N | P26: Aspergillus | Q26: State Page | R26: =VLOOKUP(P26,Categorizations!A:C,2,FALSE()) -> Aspergillus | S26: =VLOOKUP(P26,Categorizations!A:C,3,FALSE()) -> Microbial Contamination
A27: =CONCATENATE(C27,D27,J27) -> 45131ArizonaGrow Sciences | C27: 45131 | D27: Arizona | E27: https://www.azdhs.gov/policy-intergovernmental-affairs/index.php#news-release-072423 | G27: Voluntary | H27: Flower | I27: Grow Sciences Divinity | J27: Grow Sciences | L27: Y | M27: N | P27: Aspergillus | Q27: State Page | R27: =VLOOKUP(P27,Categorizations!A:C,2,FALSE()) -> Aspergillus | S27: =VLOOKUP(P27,Categorizations!A:C,3,FALSE()) -> Microbial Contamination
A28: =CONCATENATE(C28,D28,J28) -> 45131ArizonaGrow Sciences | C28: 45131 | D28: Arizona | E28: https://www.azdhs.gov/policy-intergovernmental-affairs/index.php#news-release-072423 | G28: Voluntary | H28: Flower | I28: Grow Sciences MAC | J28: Grow Sciences | L28: Y | M28: N | P28: Aspergillus | Q28: State Page | R28: =VLOOKUP(P28,Categorizations!A:C,2,FALSE()) -> Aspergillus | S28: =VLOOKUP(P28,Categorizations!A:C,3,FALSE()) -> Microbial Contamination
A29: =CONCATENATE(C29,D29,J29) -> 45131ArizonaGrow Sciences | C29: 45131 | D29: Arizona | E29: https://www.azdhs.gov/policy-intergovernmental-affairs/index.php#news-release-072423 | G29: Voluntary | H29: Flower | I29: Grow Sciences MAC | J29: Grow Sciences | L29: Y | M29: N | P29: Aspergillus | Q29: State Page | R29: =VLOOKUP(P29,Categorizations!A:C,2,FALSE()) -> Aspergillus | S29: =VLOOKUP(P29,Categorizations!A:C,3,FALSE()) -> Microbial Contamination
A30: =CONCATENATE(C30,D30,J30) -> 45131ArizonaSoothing Options | C30: 45131 | D30: Arizona | E30: https://www.azdhs.gov/policy-intergovernmental-affairs/index.php#news-release-072423 | G30: Voluntary | H30: Flower | I30: Soothing Options Gelato 41 | J30: Soothing Options | M30: N | P30: Aspergillus | Q30: State Page | R30: =VLOOKUP(P30,Categorizations!A:C,2,FALSE()) -> Aspergillus | S30: =VLOOKUP(P30,Categorizations!A:C,3,FALSE()) -> Microbial Contamination
A31: =CONCATENATE(C31,D31,J31) -> 45145ArizonaNirvana Center | C31: 45145 | D31: Arizona | E31: https://www.azdhs.gov/policy-intergovernmental-affairs/index.php#news-release-080723 | G31: Voluntary | H31: Flower | I31: Nirvana Center Cloud 9 Gummies (Grape) | J31: Nirvana Center | M31: N | P31: Salmonella | Q31: State Page | R31: =VLOOKUP(P31,Categorizations!A:C,2,FALSE()) -> Salmonella | S31: =VLOOKUP(P31,Categorizations!A:C,3,FALSE()) -> Microbial Contamination
A32: =CONCATENATE(C32,D32,J32) -> 45162ArizonaGrow Sciences | C32: 45162 | D32: Arizona | E32: https://www.azdhs.gov/policy-intergovernmental-affairs/index.php#news-release-082323 | G32: Voluntary | H32: Flower | I32: Grow Sciences Tropicana Punch | J32: Grow Sciences | L32: Y | M32: N | P32: Aspergillus | Q32: State Page | R32: =VLOOKUP(P32,Categorizations!A:C,2,FALSE()) -> Aspergillus | S32: =VLOOKUP(P32,Categorizations!A:C,3,FALSE()) -> Microbial Contamination
A33: =CONCATENATE(C33,D33,J33) -> 45219ArizonaCuraleaf | C33: 45219 | D33: Arizona | E33: https://www.azdhs.gov/policy-intergovernmental-affairs/index.php#news-release-102023 | G33: Voluntary | H33: Flower | I33: Curaleaf MnC | J33: Curaleaf | L33: Y | M33: N | P33: Aspergillus | Q33: State Page | R33: =VLOOKUP(P33,Categorizations!A:C,2,FALSE()) -> Aspergillus | S33: =VLOOKUP(P33,Categorizations!A:C,3,FALSE()) -> Microbial Contamination
A34: =CONCATENATE(C34,D34,J34) -> 45239ArizonaGLOBE FARMACY INC. | C34: 45239 | D34: Arizona | E34: https://www.azdhs.gov/policy-intergovernmental-affairs/index.php#news-release-110923 | G34: Voluntary | H34: Concentrate | I34: GLOBE FARMACY INC. EX LR GUAVA MAC | J34: GLOBE FARMACY INC. | M34: N | P34: Aspergillus | Q34: State Page | R34: =VLOOKUP(P34,Categorizations!A:C,2,FALSE()) -> Aspergillus | S34: =VLOOKUP(P34,Categorizations!A:C,3,FALSE()) -> Microbial Contamination
A35: =CONCATENATE(C35,D35,J35,2) -> 45239ArizonaGLOBE FARMACY INC.2 | C35: 45239 | D35: Arizona | E35: https://www.azdhs.gov/policy-intergovernmental-affairs/index.php#news-release-110923 | G35: Voluntary | H35: Concentrate | I35: GLOBE FARMACY INC. EX LHR ORZ | J35: GLOBE FARMACY INC. | M35: N | P35: Aspergillus | Q35: State Page | R35: =VLOOKUP(P35,Categorizations!A:C,2,FALSE()) -> Aspergillus | S35: =VLOOKUP(P35,Categorizations!A:C,3,FALSE()) -> Microbial Contamination
A36: =CONCATENATE(C36,D36,J36) -> 45257ArizonaNirvana Center | C36: 45257 | D36: Arizona | E36: https://www.azdhs.gov/policy-intergovernmental-affairs/index.php#news-release-112723 | G36: Voluntary | H36: Flower | I36: Nirvana Center Grim Reefer | J36: Nirvana Center | M36: N | P36: Aspergillus | Q36: State Page | R36: =VLOOKUP(P36,Categorizations!A:C,2,FALSE()) -> Aspergillus | S36: =VLOOKUP(P36,Categorizations!A:C,3,FALSE()) -> Microbial Contamination
A37: =CONCATENATE(C37,D37,J37) -> 45418ArizonaThe Flower Shop | C37: 45418 | D37: Arizona | E37: https://www.azdhs.gov/policy-intergovernmental-affairs/index.php#news-release-050624 | G37: Voluntary | H37: Flower | I37: The Flower Shop | J37: The Flower Shop | M37: N | P37: Aspergillus | Q37: State Page | R37: =VLOOKUP(P37,Categorizations!A:C,2,FALSE()) -> Aspergillus | S37: =VLOOKUP(P37,Categorizations!A:C,3,FALSE()) -> Microbial Contamination
A38: =CONCATENATE(C38,D38,J38) -> 45483ArizonaNature’s Wonder Inc | C38: 45483 | D38: Arizona | E38: https://www.azdhs.gov/documents/policy-intergovernmental-affairs/public-information/news-releases/news-release-for-recall-7-10-24.pdf | G38: Voluntary | H38: Concentrate | I38: DIME Mint OG | J38: Nature’s Wonder Inc | M38: N | P38: Piperonyl butoxide (Pesticide) | Q38: State Page | R38: =VLOOKUP(P38,Categorizations!A:C,2,FALSE()) -> Pesticides | S38: =VLOOKUP(P38,Categorizations!A:C,3,FALSE()) -> Pesticides
A39: =CONCATENATE(C39,J39) -> 45955Elba Holdings | C39: 45955 | D39: Arizona | E39: https://arizonastatecannabis.org/news-25oct2025 | G39: Voluntary | H39: Flower | I39: Elba Holdings | J39: Elba Holdings | P39: Aspergillus, Lead | Q39: Press | R39: =VLOOKUP(P39,Categorizations!A:C,2,FALSE()) -> Aspergillus | S39: =VLOOKUP(P39,Categorizations!A:C,3,FALSE()) -> Multiple
A40: =CONCATENATE(C40,J40) -> 46009Pressd / Baked Bros | C40: 46009 | D40: Arizona | E40: https://www.fox10phoenix.com/news/arizona-announces-marijuana-recall-amid-contamination-worries-heres-what-know | G40: Voluntary | H40: Concentrate, Edibles | I40: Pressd / Baked Bros | J40: Pressd / Baked Bros | K40: Kaycha | P40: Spinosad | Q40: Press | R40: =VLOOKUP(P40,Categorizations!A:C,2,FALSE()) -> Pesticides | S40: =VLOOKUP(P40,Categorizations!A:C,3,FALSE()) -> Pesticides
A41: =CONCATENATE(C41,J41) -> 46063Legacy & Co | C41: 46063 | D41: Arizona | E41: https://www.kvoa.com/news/arizona/marijuana-products-in-arizona-recalled-after-fungus-found-in-batches/article_a5dcfa01-e49f-48c4-8db0-0c0dd10fbdd5.html | F41: https://web.archive.org/web/20260319223623/https://www.kvoa.com/news/arizona/aspergillus-scare-prompts-arizona-marijuana-product-recall/article_cbc7c23a-dd1e-4c3f-9a01-5fc4ab80402b.html | G41: Voluntary | H41: Unspecified | I41: Legacy & Co's Super Yuzu and Nature’s Wonder's Trap Queen, | J41: Legacy & Co | M41: N | P41: Aspergillus | Q41: Press | R41: =VLOOKUP(P41,Categorizations!A:C,2,FALSE()) -> Aspergillus | S41: =VLOOKUP(P41,Categorizations!A:C,3,FALSE()) -> Microbial Contamination
A42: =CONCATENATE(C42,J42) -> 46099Legacy & Co | C42: 46099 | D42: Arizona | E42: https://web.archive.org/web/20260904154150/https://www.fox10phoenix.com/news/marijuana-azdhs-announces-voluntary-recall-amid-contamination-worries | G42: Voluntary | H42: Flower | I42: Legacy & Co's Cheech & Chongs PreRolls | J42: Legacy & Co | M42: N | P42: Aspergillus | Q42: Press | R42: =VLOOKUP(P42,Categorizations!A:C,2,FALSE()) -> Aspergillus | S42: =VLOOKUP(P42,Categorizations!A:C,3,FALSE()) -> Microbial Contamination
A43: =CONCATENATE(C43,J43) -> 46161Forever 46 | C43: 46161 | D43: Arizona | E43: https://directorsblog.health.azdhs.gov/recall-notice/ | F43: https://web.archive.org/web/20260520010915/https://www.fox10phoenix.com/news/marijuana-products-recalled-arizona-due-possible-fungus-contamination | G43: Not Specified | H43: Unspecified | I43: Forever 46, Golden Leaf Wellness, Tru infusion / Nature's Wonder | J43: Forever 46 | P43: Aspergillus | Q43: Press | R43: =VLOOKUP(P43,Categorizations!A:C,2,FALSE()) -> Aspergillus | S43: =VLOOKUP(P43,Categorizations!A:C,3,FALSE()) -> Microbial Contamination
A44: =CONCATENATE(C44,J44) -> 46204Level One Labs | C44: 46204 | D44: Arizona | E44: https://www.kvoa.com/news/arizona/arizona-marijuana-recall-possible-fungus-found-in-2-products/article_2c0b2be7-80bc-4716-aa22-c0e68eb2a394.html | F44: https://www.kvoa.com/news/arizona/arizona-marijuana-recall-possible-fungus-found-in-2-products/article_2c0b2be7-80bc-4716-aa22-c0e68eb2a394.html | G44: Voluntary | H44: Infused Flower | I44: Level One Labs | J44: Level One Labs | K44: Level One | M44: N | P44: Aspergillus | Q44: Press | R44: =VLOOKUP(P44,Categorizations!A:C,2,FALSE()) -> Aspergillus | S44: =VLOOKUP(P44,Categorizations!A:C,3,FALSE()) -> Microbial Contamination
A45: =CONCATENATE(C45,J45) -> 46224Dr Zodiak | C45: 46224 | D45: Arizona | E45: https://www.kvoa.com/news/arizona/arizona-marijuana-recall-possible-fungus-found-in-2-products/article_2c0b2be7-80bc-4716-aa22-c0e68eb2a394.html | F45: https://web.archive.org/web/20260723094334/https://www.kvoa.com/news/arizona/arizona-marijuana-recall-possible-fungus-found-in-2-products/article_2c0b2be7-80bc-4716-aa22-c0e68eb2a394.html | G45: Voluntary | H45: Infused Flower | I45: Dr. Zodiak's Moonrock Infused Bulk Snowballz and Bobby Blue's Buckshots | J45: Dr Zodiak | K45: Level One | M45: N | P45: Failed Testing for Aspergillus reported as passing | Q45: Press | R45: =VLOOKUP(P45,Categorizations!A:C,2,FALSE()) -> Multiple: Aspergillus, Lab Issue | S45: =VLOOKUP(P45,Categorizations!A:C,3,FALSE()) -> Multiple
A46: 43101CaliforniaSequoia Analytical Labs | C46: 43101 | D46: California | E46: https://www.upi.com/Top_News/US/2018/12/24/California-marijuana-recall-threatens-state-cannabis-industry/3001545673498/ | G46: Mandatory | H46: Various | I46: Unknown | J46: Sequoia Analytical Labs | M46: N | P46: Issue with Lab | Q46: Press | R46: =VLOOKUP(P46,Categorizations!A:C,2,FALSE()) -> Lab Issue | S46: =VLOOKUP(P46,Categorizations!A:C,3,FALSE()) -> Lab Issue
A47: 44587CaliforniaClaybourne Co. Head Banger | C47: 44587 | D47: California | E47: https://cannabis.ca.gov/resources/cannabis-recalls-and-safety-notices/ | G47: Mandatory | H47: Not Specified | I47: Claybourne Co. Head Banger | J47: Claybourne Co. Head Banger | M47: Y | O47: 44502 | P47: Aspergillus | Q47: State Recall Page | R47: =VLOOKUP(P47,Categorizations!A:C,2,FALSE()) -> Aspergillus | S47: =VLOOKUP(P47,Categorizations!A:C,3,FALSE()) -> Microbial Contamination
A48: 44832CaliforniaRefined Xtraction | C48: 44832 | D48: California | E48: https://cannabis.ca.gov/resources/cannabis-recalls-and-safety-notices/ | G48: Mandatory | H48: Flower | I48: Refined Xtraction | J48: Refined Xtraction | M48: N | P48: Prohibited Product | Q48: State Recall Page | R48: =VLOOKUP(P48,Categorizations!A:C,2,FALSE()) -> Prohibited Additives / Product | S48: =VLOOKUP(P48,Categorizations!A:C,3,FALSE()) -> Prohibited Additives / Product
A49: 44847CaliforniaMetta Distribution | C49: 44847 | D49: California | E49: https://cannabis.ca.gov/resources/cannabis-recalls-and-safety-notices/ | G49: Voluntary | H49: Edible | I49: Metta Distribution | J49: Metta Distribution | M49: N | P49: Aspergillus | Q49: State Recall Page | R49: =VLOOKUP(P49,Categorizations!A:C,2,FALSE()) -> Aspergillus | S49: =VLOOKUP(P49,Categorizations!A:C,3,FALSE()) -> Microbial Contamination
A50: 44918CaliforniaLakewood Libations, Inc. | C50: 44918 | D50: California | E50: https://cannabis.ca.gov/resources/cannabis-recalls-and-safety-notices/ | G50: Voluntary | H50: Beverage | I50: Lakewood Libations, Inc. | J50: Lakewood Libations, Inc. | M50: N | P50: potential packaging defect. | Q50: State Recall Page | R50: =VLOOKUP(P50,Categorizations!A:C,2,FALSE()) -> Packaging | S50: =VLOOKUP(P50,Categorizations!A:C,3,FALSE()) -> Packaging
A51: 45065CaliforniaRCW Manufacturing | C51: 45065 | D51: California | E51: https://cannabis.ca.gov/resources/cannabis-recalls-and-safety-notices/ | G51: Voluntary | H51: Beverage | I51: RCW Manufacturing | J51: RCW Manufacturing | M51: N | P51: Over-pressurization | Q51: State Recall Page | R51: =VLOOKUP(P51,Categorizations!A:C,2,FALSE()) -> Packaging | S51: =VLOOKUP(P51,Categorizations!A:C,3,FALSE()) -> Packaging
A52: 45121CaliforniaLast Minute Venture, LLC | C52: 45121 | D52: California | E52: https://cannabis.ca.gov/2023/07/voluntary-recall-last-minute-venture-llc-cannalean-brand-products/ | G52: Voluntary | H52: Tincture | I52: Last Minute Venture, LLC | J52: Last Minute Venture, LLC | M52: Y | N52: 45051 | P52: Outdated warning on labe | Q52: State Recall Page | R52: =VLOOKUP(P52,Categorizations!A:C,2,FALSE()) -> Mislabeled | S52: =VLOOKUP(P52,Categorizations!A:C,3,FALSE()) -> Mislabeled
A53: 45121CaliforniaLast Minute Venture, LLC | C53: 45250 | D53: California | E53: https://cannabis.ca.gov/resources/cannabis-recalls-and-safety-notices/left-coast-llc-lil-leftys/ | G53: Voluntary | H53: Infused pre-rolls | I53: Left Coast, LLC | J53: Left Coast, LLC | M53: Y | N53: 45057 | P53: exceed allowable THC concentration limits | Q53: State Recall Page | R53: =VLOOKUP(P53,Categorizations!A:C,2,FALSE()) -> Inaccurate THC | S53: =VLOOKUP(P53,Categorizations!A:C,3,FALSE()) -> Inaccurate THC
A54: =CONCATENATE(C54,D54,J54) -> 45267CaliforniaGrizzly Peak Farms, LLC | C54: 45267 | D54: California | E54: https://cannabis.ca.gov/resources/cannabis-recalls-and-safety-notices/grizzly-peak-farms-llc-zoap-cannabis-flower/ | G54: Voluntary | H54: Flower | I54: Grizzly Peak Farms, LLC | J54: Grizzly Peak Farms, LLC | M54: Y | N54: 45184 | P54: failed testing for the Category I pesticide, chlorfenapyr | Q54: State Recall Page | R54: =VLOOKUP(P54,Categorizations!A:C,2,FALSE()) -> Pesticides | S54: =VLOOKUP(P54,Categorizations!A:C,3,FALSE()) -> Pesticides
A55: =CONCATENATE(C55,D55,J55) -> 45301CaliforniaEchsen Industries, LLC | C55: 45301 | D55: California | E55: https://cannabis.ca.gov/resources/cannabis-recalls-and-safety-notices/echsen-industries/ | G55: Voluntary | H55: Infused Pre-Roll | I55: Echsen Industries, LLC | J55: Echsen Industries, LLC | M55: Y | N55: 45105 | O55: 45124 | P55: Pesticides: Spiromesifen | Q55: State Recall Page | R55: =VLOOKUP(P55,Categorizations!A:C,2,FALSE()) -> Pesticides | S55: =VLOOKUP(P55,Categorizations!A:C,3,FALSE()) -> Pesticides
A56: =CONCATENATE(C56,D56,J56) -> 45301CaliforniaUrban Therapies Distribution, LLC | C56: 45301 | D56: California | E56: https://cannabis.ca.gov/resources/cannabis-recalls-and-safety-notices/urban-therapies-distribution-llc/ | G56: Mandatory | H56: Flower | I56: Urban Therapies Distribution, LLC | J56: Urban Therapies Distribution, LLC | M56: Y | N56: 45119 | P56: presence of Aspergillus flavus. | Q56: State Recall Page | R56: =VLOOKUP(P56,Categorizations!A:C,2,FALSE()) -> Aspergillus | S56: =VLOOKUP(P56,Categorizations!A:C,3,FALSE()) -> Microbial Contamination
A57: =CONCATENATE(C57,D57,J57) -> 45337California90nine Bridge Co Holdings, LLC | C57: 45337 | D57: California | E57: https://recalls.cannabis.ca.gov/recalls/6761bc0d449a15805975db02 | G57: Mandatory | H57: Integrated Vaporizer | I57: 90nine Bridge Co Holdings, LLC | J57: 90nine Bridge Co Holdings, LLC | M57: Y | P57: Prohibited Product | Q57: State Recall Page | R57: =VLOOKUP(P57,Categorizations!A:C,2,FALSE()) -> Prohibited Additives / Product | S57: =VLOOKUP(P57,Categorizations!A:C,3,FALSE()) -> Prohibited Additives / Product
A58: =CONCATENATE(C58,D58,J58) -> 45343CaliforniaKind Op Corp | C58: 45343 | D58: California | E58: https://cannabis.ca.gov/resources/cannabis-recalls-and-safety-notices/roundtrip-pistachio-flower/ | G58: Mandatory | H58: Flower | I58: Kind Op Corp | J58: Kind Op Corp | M58: Y | N58: 45219 | O58: 45232 | P58: presence of Aspergillus sp. | Q58: State Recall Page | R58: =VLOOKUP(P58,Categorizations!A:C,2,FALSE()) -> Aspergillus | S58: =VLOOKUP(P58,Categorizations!A:C,3,FALSE()) -> Microbial Contamination
A59: =CONCATENATE(C59,D59,J59) -> 45343CaliforniaCypress Cannabis | C59: 45343 | D59: California | E59: https://cannabis.ca.gov/resources/cannabis-recalls-and-safety-notices/lowell-big-buds/ | G59: Mandatory | H59: Flower | I59: Cypress Cannabis | J59: Cypress Cannabis | M59: Y | O59: 45224 | P59: presence of Aspergillus sp. | Q59: State Recall Page | R59: =VLOOKUP(P59,Categorizations!A:C,2,FALSE()) -> Aspergillus | S59: =VLOOKUP(P59,Categorizations!A:C,3,FALSE()) -> Microbial Contamination
A60: =CONCATENATE(C60,D60,J60) -> 45352CaliforniaGrizzly Peak Farms, LLC | C60: 45352 | D60: California | E60: https://cannabis.ca.gov/resources/cannabis-recalls-and-safety-notices/grizzly-peak-premium-indoor-flower/ | G60: Mandatory | H60: Flower | I60: Grizzly Peak Farms, LLC | J60: Grizzly Peak Farms, LLC | M60: Y | O60: 45205 | P60: presence of Aspergillus sp. | Q60: State Recall Page | R60: =VLOOKUP(P60,Categorizations!A:C,2,FALSE()) -> Aspergillus | S60: =VLOOKUP(P60,Categorizations!A:C,3,FALSE()) -> Microbial Contamination
A61: =CONCATENATE(C61,D61,J61) -> 45355CaliforniaDGU, LLC | C61: 45355 | D61: California | E61: https://cannabis.ca.gov/resources/cannabis-recalls-and-safety-notices/panda-pen/ | G61: Voluntary | H61: Vape Cartridge | I61: DGU, LLC | J61: DGU, LLC | M61: Y | O61: 45047 | P61: obstruction of the informational label | Q61: State Recall Page | R61: =VLOOKUP(P61,Categorizations!A:C,2,FALSE()) -> Mislabeled | S61: =VLOOKUP(P61,Categorizations!A:C,3,FALSE()) -> Mislabeled
A62: =CONCATENATE(C62,D62,J62) -> 45362CaliforniaDiscount Caregivers | C62: 45362 | D62: California | E62: https://recalls.cannabis.ca.gov/recalls/6761aeec449a15805975dae9 | G62: Mandatory | H62: Flower | I62: Discount Caregivers | J62: Discount Caregivers | M62: Y | N62: 45204 | O62: 45204 | P62: presence of Aspergillus fumigatus | Q62: State Recall Page | R62: =VLOOKUP(P62,Categorizations!A:C,2,FALSE()) -> Aspergillus | S62: =VLOOKUP(P62,Categorizations!A:C,3,FALSE()) -> Microbial Contamination
A63: =CONCATENATE(C63,D63,J63) -> 45362CaliforniaJC Rad Inc. | C63: 45362 | D63: California | E63: https://recalls.cannabis.ca.gov/recalls/6761acd7d62cebee0c5c9943 | G63: Mandatory | H63: Flower | I63: JC Rad Inc. | J63: JC Rad Inc. | M63: Y | N63: 45199 | O63: 45199 | P63: presence of Aspergillus niger | Q63: State Recall Page | R63: =VLOOKUP(P63,Categorizations!A:C,2,FALSE()) -> Aspergillus | S63: =VLOOKUP(P63,Categorizations!A:C,3,FALSE()) -> Mislabeled
A64: =CONCATENATE(C64,D64,J64) -> 45371CaliforniaMammoth Distribution, Heavy Hitters, CA Manufacturing Co-op | C64: 45371 | D64: California | E64: https://recalls.cannabis.ca.gov/recalls/6761abdbd62cebee0c5c993d | G64: Mandatory | H64: Pre-Roll | I64: Mammoth Distribution, Heavy Hitters, CA Manufacturing Co-op | J64: Mammoth Distribution, Heavy Hitters, CA Manufacturing Co-op | M64: Y | N64: 45288 | O64: 45288 | P64: presence of Aspergillus niger | Q64: State Recall Page | R64: =VLOOKUP(P64,Categorizations!A:C,2,FALSE()) -> Aspergillus | S64: =VLOOKUP(P64,Categorizations!A:C,3,FALSE()) -> Mislabeled
A65: =CONCATENATE(C65,D65,J65) -> 45376CaliforniaUPNORTH Distribution | C65: 45376 | D65: California | E65: https://recalls.cannabis.ca.gov/recalls/6761bccb449a15805975db06 | G65: Mandatory | H65: Flower | I65: UPNORTH Distribution | J65: UPNORTH Distribution | M65: Y | N65: 45184 | O65: 45184 | P65: presence of Aspergillus terreus | Q65: State Recall Page | R65: =VLOOKUP(P65,Categorizations!A:C,2,FALSE()) -> Aspergillus | S65: =VLOOKUP(P65,Categorizations!A:C,3,FALSE()) -> Microbial Contamination
A66: =CONCATENATE(C66,D66,J66) -> 45380CaliforniaMalibu Gold, LLC | C66: 45380 | D66: California | E66: https://recalls.cannabis.ca.gov/recalls/6761b4b3449a15805975dafe | G66: Voluntary | H66: Flower | I66: Malibu Gold, LLC | J66: Malibu Gold, LLC | M66: Y | N66: 45131 | O66: 45131 | P66: inaccurate THC content labeling | Q66: State Recall Page | R66: =VLOOKUP(P66,Categorizations!A:C,2,FALSE()) -> Inaccurate THC | S66: =VLOOKUP(P66,Categorizations!A:C,3,FALSE()) -> Inaccurate THC
A67: =CONCATENATE(C67,D67,J67) -> 45391CaliforniaNorthern Emeralds | C67: 45391 | D67: California | E67: https://recalls.cannabis.ca.gov/recalls/6761b362449a15805975daf9 | G67: Mandatory | H67: Flower | I67: Northern Emeralds | J67: Northern Emeralds | M67: Y | N67: 45162 | O67: 45162 | P67: presence of Aspergillus sp. | Q67: State Recall Page | R67: =VLOOKUP(P67,Categorizations!A:C,2,FALSE()) -> Aspergillus | S67: =VLOOKUP(P67,Categorizations!A:C,3,FALSE()) -> Microbial Contamination
A68: =CONCATENATE(C68,D68,J68) -> 45401CaliforniaUrbina, Inc | C68: 45401 | D68: California | E68: https://cannabis.ca.gov/resources/cannabis-recalls-and-safety-notices/8-track-pre-roll/ | G68: Mandatory | H68: Pre-Roll | I68: Urbina, Inc | J68: Urbina, Inc | M68: Y | N68: 45191 | O68: 45191 | P68: presence of Aspergillus niger and Aspergillus flavus, and due to inaccurate labeling, that reports more THC than the product contains. | Q68: State Recall Page | R68: =VLOOKUP(P68,Categorizations!A:C,2,FALSE()) -> Multiple (Aspergillus, THC Inflation) | S68: =VLOOKUP(P68,Categorizations!A:C,3,FALSE()) -> Multiple
A69: =CONCATENATE(C69,D69,J69) -> 45407CaliforniaSnap Distro SV | C69: 45407 | D69: California | E69: https://recalls.cannabis.ca.gov/recalls/6761bc23449a15805975db04 | G69: Mandatory | H69: Pre-Roll | I69: Snap Distro SV | J69: Snap Distro SV | M69: Y | N69: 45222 | O69: 45222 | P69: presence of Aspergillus niger and Aspergillus flavus, and due to inaccurate labeling, that reports more THC than the product contains. | Q69: State Recall Page | R69: =VLOOKUP(P69,Categorizations!A:C,2,FALSE()) -> Multiple (Aspergillus, THC Inflation) | S69: =VLOOKUP(P69,Categorizations!A:C,3,FALSE()) -> Multiple
A70: =CONCATENATE(C70,D70,J70) -> 45418CaliforniaTBP Indoor Facilities, Inc. | C70: 45418 | D70: California | E70: https://cannabis.ca.gov/resources/cannabis-recalls-and-safety-notices/canndescent-california-100-whole-flower-pre-rolls/ | G70: Mandatory | H70: Pre-Roll | I70: TBP Indoor Facilities, Inc. | J70: TBP Indoor Facilities, Inc. | M70: Y | O70: 45244 | P70: presence of Aspergillus spp. and due to inaccurate labeling that reports more cannabinoid content than the product contains. | Q70: State Recall Page | R70: =VLOOKUP(P70,Categorizations!A:C,2,FALSE()) -> Multiple (Aspergillus, THC Inflation) | S70: =VLOOKUP(P70,Categorizations!A:C,3,FALSE()) -> Multiple
A71: =CONCATENATE(C71,D71,J71) -> 45421CaliforniaJDI Farms | C71: 45421 | D71: California | E71: https://cannabis.ca.gov/resources/cannabis-recalls-and-safety-notices/cali-kosher-flower/ | G71: Voluntary | H71: Flower | I71: JDI Farms | J71: JDI Farms | M71: Y | O71: 45126 | P71: inaccurate labeling, that reports more cannabinoid content | Q71: State Recall Page | R71: =VLOOKUP(P71,Categorizations!A:C,2,FALSE()) -> Inaccurate THC | S71: =VLOOKUP(P71,Categorizations!A:C,3,FALSE()) -> Inaccurate THC
A72: =CONCATENATE(C72,D72,J72) -> 45429CaliforniaCrafted Canopy Co. LLC | C72: 45429 | D72: California | E72: https://cannabis.ca.gov/resources/cannabis-recalls-and-safety-notices/lax-packs-premium-flower/ | G72: Mandatory | H72: Flower | I72: Crafted Canopy Co. LLC | J72: Crafted Canopy Co. LLC | M72: Y | O72: 45160 | P72: Aspergillus fumigatus, and due to inaccurate labeling | Q72: State Recall Page | R72: =VLOOKUP(P72,Categorizations!A:C,2,FALSE()) -> Multiple (Aspergillus, THC Inflation) | S72: =VLOOKUP(P72,Categorizations!A:C,3,FALSE()) -> Multiple
A73: =CONCATENATE(C73,D73,J73) -> 45436CaliforniaEpic Bros Enterprises, Inc. | C73: 45436 | D73: California | E73: https://recalls.cannabis.ca.gov/recalls/67607f90e7333c2117ce13c2 | G73: Voluntary | H73: Beverage | I73: Epic Bros Enterprises, Inc. | J73: Epic Bros Enterprises, Inc. | M73: Y | O73: 45400 | P73: packaging safety issues | Q73: State Recall Page | R73: =VLOOKUP(P73,Categorizations!A:C,2,FALSE()) -> Packaging | S73: =VLOOKUP(P73,Categorizations!A:C,3,FALSE()) -> Packaging
A74: =CONCATENATE(C74,D74,J74) -> 45446CaliforniaPaet Real Estate LLC | C74: 45446 | D74: California | E74: https://recalls.cannabis.ca.gov/recalls/676075d467bff701781d9596 | G74: Mandatory | H74: Flower | I74: Paet Real Estate LLC | J74: Paet Real Estate LLC | M74: Y | O74: 45208 | P74: presence of Aspergillus niger, and due to inaccurate labeling | Q74: State Recall Page | R74: =VLOOKUP(P74,Categorizations!A:C,2,FALSE()) -> Multiple (Aspergillus, THC Inflation) | S74: =VLOOKUP(P74,Categorizations!A:C,3,FALSE()) -> Multiple
A75: =CONCATENATE(C75,D75,J75) -> 45455CaliforniaShield Management Group, LLC | C75: 45455 | D75: California | E75: https://recalls.cannabis.ca.gov/recalls/67608282141ebf4b23e92734 | G75: Voluntary | H75: Flower | I75: WEST COAST CURE PREMIUM CURE Flower | J75: Shield Management Group, LLC | M75: Y | O75: 45331 | P75: inaccurate labeling that reports more cannabinoid content | Q75: State Recall Page | R75: =VLOOKUP(P75,Categorizations!A:C,2,FALSE()) -> Inaccurate THC | S75: =VLOOKUP(P75,Categorizations!A:C,3,FALSE()) -> Inaccurate THC
A76: =CONCATENATE(C76,D76,J76) -> 45468CaliforniaAlkhemist DM LLC | C76: 45468 | D76: California | E76: https://recalls.cannabis.ca.gov/recalls/67608d79141ebf4b23e92757 | G76: Mandatory | H76: Vape Cartridge | I76: CUREpen PREMIUM THC OIL Vape Cartridge | J76: Alkhemist DM LLC | M76: Y | O76: 45198 | P76: presence of the pesticide chlorfenapyr | Q76: State Recall Page | R76: =VLOOKUP(P76,Categorizations!A:C,2,FALSE()) -> Pesticides | S76: =VLOOKUP(P76,Categorizations!A:C,3,FALSE()) -> Packaging
A77: =CONCATENATE(C77,D77,J77) -> 45475CaliforniaShield Management Group, LLC | C77: 45475 | D77: California | E77: https://recalls.cannabis.ca.gov/recalls/67607a66e7333c2117ce13ab | G77: Mandatory | H77: Vape Cartridge | I77: WCC CUREpen PREMIUM THC OIL Vape Cartridge | J77: Shield Management Group, LLC | M77: Y | O77: 45177 | P77: presence of the pesticide chlorfenapyr | Q77: State Recall Page | R77: =VLOOKUP(P77,Categorizations!A:C,2,FALSE()) -> Pesticides | S77: =VLOOKUP(P77,Categorizations!A:C,3,FALSE()) -> Packaging
A78: =CONCATENATE(C78,D78,J78) -> 45475CaliforniaShield Management Group, LLC | C78: 45475 | D78: California | E78: https://cannabis.ca.gov/resources/cannabis-recalls-and-safety-notices/west-coast-cure-live-resin-vape-cartridge/ | G78: Mandatory | H78: Vape Cartridge | I78: WEST COAST CURE CUREpen Vape Cartridge | J78: Shield Management Group, LLC | M78: Y | O78: 45197 | P78: presence of the pesticide chlorfenapyr | Q78: State Recall Page | R78: =VLOOKUP(P78,Categorizations!A:C,2,FALSE()) -> Pesticides | S78: =VLOOKUP(P78,Categorizations!A:C,3,FALSE()) -> Packaging
A79: =CONCATENATE(C79,D79,J79) -> 45475CaliforniaShield Management Group, LLC | C79: 45475 | D79: California | E79: https://cannabis.ca.gov/resources/cannabis-recalls-and-safety-notices/west-coast-cure-curepen-vape-cartridge/ | G79: Mandatory | H79: Vape Cartridge | I79: WEST COAST CURE LIVE RESIN Vape Cartridge | J79: Shield Management Group, LLC | M79: Y | O79: 45197 | P79: presence of the pesticide chlorfenapyr | Q79: State Recall Page | R79: =VLOOKUP(P79,Categorizations!A:C,2,FALSE()) -> Pesticides | S79: =VLOOKUP(P79,Categorizations!A:C,3,FALSE()) -> Packaging
A80: =CONCATENATE(C80,D80,J80) -> 45490CaliforniaK.U.S.H. (KINDER UNDERSTANDING SENSITIVE HEALING) COLLECTIVE | C80: 45490 | D80: California | E80: https://cannabis.ca.gov/resources/cannabis-recalls-and-safety-notices/backpackboyz-premium-vape/ | G80: Mandatory | H80: Vape Cartridge | I80: CIRCLES Cannabis Oil Vaporizer Vape Cartridge | J80: K.U.S.H. (KINDER UNDERSTANDING SENSITIVE HEALING) COLLECTIVE | M80: Y | N80: 45192 | O80: 45187 | P80: presence of the pesticide chlorfenapyr | Q80: State Recall Page | R80: =VLOOKUP(P80,Categorizations!A:C,2,FALSE()) -> Pesticides | S80: =VLOOKUP(P80,Categorizations!A:C,3,FALSE()) -> Packaging
A81: =CONCATENATE(C81,D81,J81) -> 45490CaliforniaK.U.S.H. (KINDER UNDERSTANDING SENSITIVE HEALING) COLLECTIVE | C81: 45490 | D81: California | E81: https://cannabis.ca.gov/resources/cannabis-recalls-and-safety-notices/circles-cannabis-oil-vaporizer/ | G81: Mandatory | H81: Integrated Vaporizer | I81: Backpackboyz PREMIUM VAPE Integrated Vaporizer | J81: K.U.S.H. (KINDER UNDERSTANDING SENSITIVE HEALING) COLLECTIVE | M81: Y | N81: 45359 | O81: 45363 | P81: presence of the pesticide chlorfenapyr | Q81: State Recall Page | R81: =VLOOKUP(P81,Categorizations!A:C,2,FALSE()) -> Pesticides | S81: =VLOOKUP(P81,Categorizations!A:C,3,FALSE()) -> Packaging
A82: =CONCATENATE(C82,D82,J82) -> 45497CaliforniaThe Bake Shop LA | C82: 45497 | D82: California | E82: https://recalls.cannabis.ca.gov/recalls/67608170e7333c2117ce13c5 | G82: Mandatory | H82: Pre-Roll | I82: The Bake Shop LA | J82: The Bake Shop LA | M82: Y | N82: 45436 | O82: 45446 | P82: presence of Aspergillus flavus. | Q82: State Recall Page | R82: =VLOOKUP(P82,Categorizations!A:C,2,FALSE()) -> Aspergillus | S82: =VLOOKUP(P82,Categorizations!A:C,3,FALSE()) -> Microbial Contamination
A83: =CONCATENATE(C83,D83,J83) -> 45503CaliforniaGC Global, LLC | C83: 45503 | D83: California | E83: https://cannabis.ca.gov/resources/cannabis-recalls-and-safety-notices/kush-creaturz-flower/ | G83: Mandatory | H83: Flower | I83: Kush Creaturz Donny Dank | J83: GC Global, LLC | M83: Y | N83: 45161 | O83: 45177 | P83: labeling attractive to Children | Q83: State Recall Page | R83: =VLOOKUP(P83,Categorizations!A:C,2,FALSE()) -> Attractive Label | S83: =VLOOKUP(P83,Categorizations!A:C,3,FALSE()) -> Packaging
A84: =CONCATENATE(C84,D84,J84) -> 45503CaliforniaKush Creaturz | C84: 45503 | D84: California | E84: https://cannabis.ca.gov/resources/cannabis-recalls-and-safety-notices/kush-creaturz-flower/ | G84: Mandatory | H84: Flower | I84: Kush Creaturz OG Suzie Slop | J84: Kush Creaturz | M84: Y | N84: 45161 | O84: 45177 | P84: labeling attractive to Children | Q84: State Recall Page | R84: =VLOOKUP(P84,Categorizations!A:C,2,FALSE()) -> Attractive Label | S84: =VLOOKUP(P84,Categorizations!A:C,3,FALSE()) -> Packaging
A85: =CONCATENATE(C85,D85,J85) -> 45503CaliforniaKush Creaturz | C85: 45503 | D85: California | E85: https://cannabis.ca.gov/resources/cannabis-recalls-and-safety-notices/kush-creaturz-flower/ | G85: Mandatory | H85: Flower | I85: Kush Creaturz Randy Resin | J85: Kush Creaturz | M85: Y | N85: 45294 | O85: 45309 | P85: labeling attractive to Children | Q85: State Recall Page | R85: =VLOOKUP(P85,Categorizations!A:C,2,FALSE()) -> Attractive Label | S85: =VLOOKUP(P85,Categorizations!A:C,3,FALSE()) -> Packaging
A86: =CONCATENATE(C86,D86,J86) -> 45503CaliforniaKush Creaturz | C86: 45503 | D86: California | E86: https://cannabis.ca.gov/resources/cannabis-recalls-and-safety-notices/kush-creaturz-flower/ | G86: Mandatory | H86: Flower | I86: Kush Creaturz Marty Mids | J86: Kush Creaturz | M86: Y | N86: 45294 | O86: 45296 | P86: labeling attractive to Children | Q86: State Recall Page | R86: =VLOOKUP(P86,Categorizations!A:C,2,FALSE()) -> Attractive Label | S86: =VLOOKUP(P86,Categorizations!A:C,3,FALSE()) -> Packaging
A87: =CONCATENATE(C87,D87,J87) -> 45503CaliforniaKush Creaturz | C87: 45503 | D87: California | E87: https://cannabis.ca.gov/resources/cannabis-recalls-and-safety-notices/kush-creaturz-flower/ | G87: Mandatory | H87: Flower | I87: Kush Creaturz Limonene Linda | J87: Kush Creaturz | M87: Y | N87: 45161 | O87: 45177 | P87: labeling attractive to Children | Q87: State Recall Page | R87: =VLOOKUP(P87,Categorizations!A:C,2,FALSE()) -> Attractive Label | S87: =VLOOKUP(P87,Categorizations!A:C,3,FALSE()) -> Packaging
A88: =CONCATENATE(C88,D88,J88) -> 45503CaliforniaKush Creaturz | C88: 45503 | D88: California | E88: https://cannabis.ca.gov/resources/cannabis-recalls-and-safety-notices/kush-creaturz-flower/ | G88: Voluntary | H88: Flower | I88: Kush Creaturz Frank the Fuego Man | J88: Kush Creaturz | M88: Y | N88: 45293 | O88: 45295 | P88: labeling attractive to Children | Q88: State Recall Page | R88: =VLOOKUP(P88,Categorizations!A:C,2,FALSE()) -> Attractive Label | S88: =VLOOKUP(P88,Categorizations!A:C,3,FALSE()) -> Packaging
A89: =CONCATENATE(C89,J89) -> 45505Cypress Manufacturing | C89: 45505 | D89: California | E89: https://cannabis.ca.gov/resources/cannabis-recalls-and-safety-notices/lowell-35s-10-tall-pre-roll/ | G89: Mandatory | H89: Pre-Roll | I89: Lowell 35’s 10 Tall Pre-Rolls Afternoon Delight | J89: Cypress Manufacturing | M89: Y | N89: 45413 | O89: 45421 | P89: Aspergillus niger | Q89: State Recall Page | R89: =VLOOKUP(P89,Categorizations!A:C,2,FALSE()) -> Aspergillus | S89: =VLOOKUP(P89,Categorizations!A:C,3,FALSE()) -> Microbial Contamination
A90: =CONCATENATE(C90,J90) -> 45512Fluids Manufacturing, Inc. | C90: 45512 | D90: California | E90: https://recalls.cannabis.ca.gov/recalls/67607f00e7333c2117ce13bd | G90: Mandatory | H90: Flower | I90: Almora Naturally Better Single Origin Cannabis Flower | J90: Fluids Manufacturing, Inc. | M90: Y | N90: 45418 | O90: 45421 | P90: Aspergillus niger | Q90: State Recall Page | R90: =VLOOKUP(P90,Categorizations!A:C,2,FALSE()) -> Aspergillus | S90: =VLOOKUP(P90,Categorizations!A:C,3,FALSE()) -> Microbial Contamination
A91: =CONCATENATE(C91,J91) -> 45512Mammoth Distribution, Heavy Hitters | C91: 45512 | D91: California | E91: https://recalls.cannabis.ca.gov/recalls/67607f00e7333c2117ce13bd | G91: Mandatory | H91: Flower | I91: Almora Naturally Better Single Origin Cannabis Flower | J91: Mammoth Distribution, Heavy Hitters | M91: Y | N91: 45418 | O91: 45427 | P91: Adulterated: Microbial Contamination (Aspergillus niger) | Q91: State Recall Page | R91: =VLOOKUP(P91,Categorizations!A:C,2,FALSE()) -> Aspergillus | S91: =VLOOKUP(P91,Categorizations!A:C,3,FALSE()) -> Microbial Contamination
A92: =CONCATENATE(C92,J92) -> 45520Alkhemist DM LLC | C92: 45520 | D92: California | E92: https://recalls.cannabis.ca.gov/recalls/676060ab2dec600a5fdab838 | G92: Mandatory | H92: Pre-Roll | I92: Glass House Farms Cannabis Flower Pre-Roll | J92: Alkhemist DM LLC | M92: Y | N92: 45412 | O92: 45386 | P92: Adulterated: Microbial Contamination (Aspergillus flavus) | Q92: State Recall Page | R92: =VLOOKUP(P92,Categorizations!A:C,2,FALSE()) -> Aspergillus | S92: =VLOOKUP(P92,Categorizations!A:C,3,FALSE()) -> Microbial Contamination
A93: =CONCATENATE(C93,J93) -> 45525Purple Star MD Collective | C93: 45525 | D93: California | E93: https://recalls.cannabis.ca.gov/recalls/67607b92e7333c2117ce13b7 | G93: Mandatory | H93: Flower | I93: Flor Flower | J93: Purple Star MD Collective | M93: Y | N93: 45433 | O93: 45439 | P93: Adulterated: Microbial Contamination (Aspergillus niger) | Q93: State Recall Page | R93: =VLOOKUP(P93,Categorizations!A:C,2,FALSE()) -> Aspergillus | S93: =VLOOKUP(P93,Categorizations!A:C,3,FALSE()) -> Microbial Contamination
A94: =CONCATENATE(C94,J94) -> 45526BTD, Inc. | C94: 45526 | D94: California | E94: https://recalls.cannabis.ca.gov/recalls/67607b87e7333c2117ce13b5 | G94: Mandatory | H94: Flower | I94: NHPR Flower | J94: BTD, Inc. | M94: Y | N94: 45414 | O94: 45414 | P94: Adulterated: Microbial Contamination (Aspergillus niger) | Q94: State Recall Page | R94: =VLOOKUP(P94,Categorizations!A:C,2,FALSE()) -> Aspergillus | S94: =VLOOKUP(P94,Categorizations!A:C,3,FALSE()) -> Microbial Contamination
A95: =CONCATENATE(C95,J95) -> 45533Shield Management Group, LLC | C95: 45533 | D95: California | E95: https://recalls.cannabis.ca.gov/recalls/676061d02dec600a5fdab847 | G95: Mandatory | H95: Concentrate | I95: West Coast Cure Live Resin Diamonds Concentrate | J95: Shield Management Group, LLC | M95: Y | N95: 45224 | O95: 45232 | P95: Adulterated: Pesticide Category I Contamination (Chlorfenapyr) | Q95: State Recall Page | R95: =VLOOKUP(P95,Categorizations!A:C,2,FALSE()) -> Pesticides | S95: =VLOOKUP(P95,Categorizations!A:C,3,FALSE()) -> Pesticides
A96: =CONCATENATE(C96,J96) -> 45533Shield Management Group, LLC | C96: 45533 | D96: California | E96: https://recalls.cannabis.ca.gov/recalls/67607a8ce7333c2117ce13b0 | G96: Mandatory | H96: Vape Cartridges | I96: CUREpen Premium THC Oil Vape Cartridge | J96: Shield Management Group, LLC | M96: Y | N96: 45163 | O96: 45183 | P96: Adulterated: Pesticide Category I Contamination (Chlorfenapyr) | Q96: State Recall Page | R96: =VLOOKUP(P96,Categorizations!A:C,2,FALSE()) -> Pesticides | S96: =VLOOKUP(P96,Categorizations!A:C,3,FALSE()) -> Pesticides
A97: =CONCATENATE(C97,J97) -> 45541K.U.S.H. COLLECTIVE | C97: 45541 | D97: California | E97: https://recalls.cannabis.ca.gov/recalls/6760641e2dec600a5fdab874 | G97: Mandatory | H97: Vape Cartridges | I97: Cloud Cannabis Oil Vaporizer Vape Cartridge | J97: K.U.S.H. COLLECTIVE | M97: Y | N97: 45320 | O97: 45352 | P97: Adulterated: Pesticide Category I Contamination (Chlorfenapyr) | Q97: State Recall Page | R97: =VLOOKUP(P97,Categorizations!A:C,2,FALSE()) -> Pesticides | S97: =VLOOKUP(P97,Categorizations!A:C,3,FALSE()) -> Pesticides
A98: =CONCATENATE(C98,J98) -> 45541K.U.S.H. COLLECTIVE | C98: 45541 | D98: California | E98: https://recalls.cannabis.ca.gov/recalls/676071c2348fc6641c270943 | G98: Mandatory | H98: Vape Cartridges | I98: Circles Cannabis Oil Vaporizer Vape Cartridge | J98: K.U.S.H. COLLECTIVE | M98: Y | N98: 45359 | O98: 45372 | P98: Adulterated: Pesticide Category I Contamination (Chlorfenapyr) | Q98: State Recall Page | R98: =VLOOKUP(P98,Categorizations!A:C,2,FALSE()) -> Pesticides | S98: =VLOOKUP(P98,Categorizations!A:C,3,FALSE()) -> Pesticides
A99: =CONCATENATE(C99,J99) -> 45541GC Global, LLC | C99: 45541 | D99: California | E99: https://recalls.cannabis.ca.gov/recalls/676078ffe7333c2117ce13a3 | G99: Mandatory | H99: Vape Cartridges | I99: Retro Hits Premium Cannabis Distillate Vape Cartridge | J99: GC Global, LLC | M99: Y | N99: 45330 | O99: 45342 | P99: Misbranded: Other | Q99: State Recall Page | R99: =VLOOKUP(P99,Categorizations!A:C,2,FALSE()) -> Attractive Label | S99: =VLOOKUP(P99,Categorizations!A:C,3,FALSE()) -> Packaging
A100: =CONCATENATE(C100,J100) -> 45546Scislc, LLC | C100: 45546 | D100: California | E100: https://recalls.cannabis.ca.gov/recalls/675cd072db9d2f38e6a8bfc9 | G100: Mandatory | H100: Infused Pre-Roll | I100: CLSICS 10 Hash Infused Dog Walkers Infused Pre-Roll | J100: Scislc, LLC | M100: Y | N100: 45300 | O100: 45316 | P100: Adulterated: Pesticide Category I Contamination (Paclobutrazol) | Q100: State Recall Page | R100: =VLOOKUP(P100,Categorizations!A:C,2,FALSE()) -> Pesticides | S100: =VLOOKUP(P100,Categorizations!A:C,3,FALSE()) -> Pesticides
...

Sheet Categorizations
A1: Reason | B1: Category | C1: Tight Cat
A2: Bifenthrin and Chlorfenapyr | B2: Pesticides | C2: Pesticides
A3: Pyrethrins and Piperonyl butoxide | B3: Pesticides | C3: Pesticides
A4: Abamectin | B4: Pesticides | C4: Pesticides
A5: imidacloprid and myclobutanil | B5: Pesticides | C5: Pesticides
A6: permethrin, spiromesifen | B6: Pesticides | C6: Pesticides
A7: malathion | B7: Pesticides | C7: Pesticides
A8: Ethephon | B8: Pesticides | C8: Pesticides
A9: unspecified pesticide | B9: Pesticides | C9: Pesticides
A10: Diuron | B10: Pesticides | C10: Pesticides
A11: Bifenthrin and Diuron | B11: Pesticides | C11: Pesticides
A12: Pyriproxyfen | B12: Pesticides | C12: Pesticides
... A314: Methylene Chloride | B314: Solvent | C314: Solvent

Sheet Rescinded
B1: 46251 | C1: 46252 | D1: California | F1: https://web.archive.org/web/20260904163707/https://recalls.cannabis.ca.gov/recalls/6a7df35de9866a4e68ffcaec | G1: Voluntary | H1: Beverage | I1: St Ides Beverage | J1: LP Roadrunner Logistics LLC | M1: Y | P1: incomplete and incorrect regulatory compliance testing. | Q1: State Recall Page | R1: =VLOOKUP(P1,Categorizations!A:C,2,FALSE()) -> Incomplete Testing | S1: =VLOOKUP(P1,Categorizations!A:C,3,FALSE()) -> Lab Issue | T1: Pabst Labs

Sheet Categorization Explode Multiple
A1: Reason | B1: Category | C1: Tight Cat
A2: Bifenthrin and Chlorfenapyr | B2: Pesticides | C2: Pesticides
A3: Pyrethrins and Piperonyl butoxide | B3: Pesticides | C3: Pesticides
A4: Abamectin | B4: Pesticides | C4: Pesticides
A5: imidacloprid and myclobutanil | B5: Pesticides | C5: Pesticides
A6: permethrin, spiromesifen | B6: Pesticides | C6: Pesticides
A7: malathion | B7: Pesticides | C7: Pesticides
A8: Ethephon | B8: Pesticides | C8: Pesticides
A9: unspecified pesticide | B9: Pesticides | C9: Pesticides
A10: Diuron | B10: Pesticides | C10: Pesticides
A11: Bifenthrin and Diuron | B11: Pesticides | C11: Pesticides
A12: Pyriproxyfen | B12: Pesticides | C12: Pesticides
... A331: Spinosad | B331: Pesticides | C331: Pesticides

Sheet Allowable Pesticide List Links
A1: State | B1: Data
A2: Alabama
A3: Alaska | B3: No | C3: https://dec.alaska.gov/media/xnzhit1j/cannabis-pesticides.pdf
A4: Arizona | B4: Yes
A5: Arkansas | B5: No
A6: California | B6: Yes
A7: Colorado | B7: Yes | C7: https://docs.google.com/spreadsheets/d/14MpUpc-DCLQgKCfcz2uNeroNCO4ILNHA6lwM0CawudU/edit?gid=366976881#gid=366976881
A8: Connecticut | B8: No
A9: Delaware | B9: No
A10: Florida | B10: No
A11: Georgia | B11: No
A12: Hawaii | B12: No
A13: Idaho
A14: Illinois | B14: No
A15: Indiana
A16: Iowa
A17: Kansas
A18: Kentucky | B18: No
A19: Louisiana | B19: No
A20: Maine | B20: No
A21: Maryland | B21: No
A22: Massachusetts | B22: No
A23: Michigan | B23: Yes
A24: Minnesota | B24: No
A25: Mississippi | B25: No
A26: Missouri | B26: No
A27: Montana | B27: Yes
A28: Nebraska
A29: Nevada | B29: Yes
A30: New Hampshire | B30: No
A31: New Jersey | B31: Yes
A32: New Mexico | B32: Yes
A33: New York | B33: No
A34: North Dakota | B34: No
A35: Ohio | B35: Yes
A36: Oklahoma | B36: Yes
A37: Oregon | B37: Yes
A38: Pennsylvania | B38: No
A39: Rhode Island | B39: No
A40: South Carolina
A41: South Dakota | B41: No
A42: Tennessee
A43: Texas
A44: Utah
A45: Vermont | B45: No
A46: Virginia
A47: Washington | B47: Yes
A48: West Virginia | B48: No
A49: Wisconsin
A50: Wyoming
A51: District of Columbia | B51: No

Sheet Pesticides
A1: Reason | B1: Pesticides
A2: Pyrethrins and Piperonyl butoxide | B2: Pyrethrins
A3: Pyrethrins and Piperonyl butoxide | B3: Piperonyl butoxide
A4: Abamectin | B4: Abamectin
A5: Bifenthrin and Chlorfenapyr | B5: Bifenthrin
A6: Bifenthrin and Chlorfenapyr | B6: Chlorfenapyr
A7: myclobutanil and etoxazole | B7: Myclobutanil
A8: myclobutanil and etoxazole | B8: Etoxazole
A9: imidacloprid and myclobutanil | B9: Myclobutanil
A10: imidacloprid and myclobutanil | B10: Imidacloprid
A11: permethrin, spiromesifen | B11: spiromesifen
A12: permethrin, spiromesifen | B12: permethrin
... A130: Spinosad | B130: Spinosad

Sheet Pesticide Info
A1: Pesticide Name | B1: Colorado | C1: California | D1: Group1 | E1: Group2 | F1: Group3
A2: Abamectin | D2: insecticide | E2: acaricide | F2: nematicide
A3: Avermectin | D3: insecticide
A4: Azoxystrobin | D4: broad spectrum systemic fungicide
A5: Bifenazate | D5: miticide | E5: systemic and non-systemic miticides | F5: acaricide
A6: Bifenthrin | D6: insecticide | E6: pyrethoid insecticide
A7: Chlorfenapyr | D7: insecticide
A8: Cypermethrin
A9: Daminozide
A10: Dichlenobil
A11: Diphenylamine (DPA)
A12: Diuron
A13: Ethephon
A14: Etoxazole
A15: Fluopyram
A16: Fluopyram.
A17: hexythiazox
A18: Imidacloprid
A19: indolbutyric acid (IBA) | B19: Onlist | C19: Onlist
A20: malathion
A21: Malathion A
A22: Myclobutanil
A23: O-phenylphenol
A24: O-phenylphenol (OPP)
A25: paclobutrazal
A26: paclobutrazol
A27: permethrin
A28: Piperonyl butoxide | B28: Onlist | C28: Onlist
A29: Propiconazole
A30: Pyrethrins | B30: Onlist | C30: Onlist
A31: Pyridaben
A32: Pyrimethanil
A33: Pyriproxyfen
A34: Spinosad
A35: Spinosad
A36: Spinosyn
A37: Spinosyn A
A38: Spiromefesin
A39: spiromesifen
A40: Spiromesifin
A41: Tebuconazole
A42: Thiabendazole
... A46: Unspecified Pesticides

Sheet California Allowables
A1: Can Be Used on Cannabis? Y or N | B1: Restrictions & Exceptions | C1: Registrant | D1: EPA Registration Number | E1: Active Ingredient(s) | F1: Pesticide Type | G1: DPR Stamped Date* For Internal Use Only
A2: Y | B2: This product is restricted to use in nurseries. | C2: OHP, Inc. | D2: 70051-19-AA-59807 | E2: Isaria fumosorosea apopka strain 97 (ATCC 20874) | F2: Insecticide | G2: 42653
A3: Y | B3: N/A | C3: Becker Microbial Products, Inc. | D3: 62637-3-ZA | E3: Bacilllus thuringiensis subspecies israelensis strain BMP 144 | F3: Insecticide | G3: 41456
A4: Y | B4: For mosquito control as directed on the label | C4: Becker Microbial Products, Inc. | D4: 62637-1-ZA | E4: Bacilllus thuringiensis subspecies israelensis strain BMP 144 | F4: Insecticide | G4: 4/40/22
A5: Y | B5: This product is an adjuvant. It can be used with other registered products that meet the legal criteria for use on cannabis, but not independently. | C5: Aquatrols Corporation of America | D5: 9037-50003-AA | E5: N/A | F5: Adjuvant | G5: 43720
A6: Y | B6: This product is an adjuvant. It can be used with other registered products that meet the legal criteria for use on cannabis, but not independently. | C6: Aquatrols Corporation of America | D6: 9037-50003-AA | E6: N/A | F6: Adjuvant | G6: 39486
A7: Y | B7: N/A | C7: Athena Ag, Inc. | D7: 82752-1-AA-93752 | E7: IBA (indole-3-butyric acid) | F7: Plant Growth Regulator | G7: 43816
A8: Y | B8: N/A | C8: Atticus, LLC | D8: 91234-306-AA | E8: Azadirachtin | F8: Insecticide | G8: 45658
A9: Y | B9: N/A | C9: Atticus, LLC | D9: 91234-305-AA | E9: Azadirachtin | F9: Miticide, Insecticide, Nematacide | G9: 45965
A10: Y | B10: This product is restricted to indoor use, including greenhouses. | C10: Biosafe Systems, LLC | D10: 70299-23-AA | E10: Ammonium nonanoate | F10: Herbicide | G10: 41754
A11: Y | B11: N/A | C11: Gowan Company, LLC | D11: 71908-1-AA-10163 | E11: Azadirachtin | F11: Insecticide, Insect Repellent | G11: 40521
A12: Y | B12: N/A | C12: Biosafe Systems, LLC | D12: 70299-17-AA | E12: Azadirachtin | F12: Insecticide, Nematicide | G12: 43133
A13: Y | B13: N/A | C13: Parry America Inc. | D13: 71908-1-AA-81268 | E13: Azadirachtin | F13: Insecticide, Miticide, Nematicide | G13: 43476
A14: Y | B14: N/A | C14: Arborjet, Inc. | D14: 81899-4-AA-74578 | E14: Azadirachtin | F14: Insecticide, Nematicide | G14: 43613
A15: Y | B15: N/A | C15: Arborjet, Inc. | D15: 81899-4-ZA-74578 | E15: Azadirachtin | F15: Insecticide | G15: 44320
A16: Y | B16: N/A | C16: OHP, Inc. | D16: 70051-9-AA-59807 | E16: Azadirachtin | F16: Insecticide | G16: 44743
... A23: Y | B23: N/A | C23: Bonide Products, LLC | D23: 67702-54-ZB-4 | E23: Caprylic acid, capric acid | F23: Herbicide, Algaecide | G23: 43182
A24: Y | C24: Certis USA, LLC | D24: 82074-5-ZA | E24: Pyrethrins, Beauveria bassiana strain: GHA | F24: Insecticide | G24: 44257
A25: Y | B25: N/A | C25: Lawn And Garden Products, Inc. | D25: 1021-1771-AA-54705 | E25: Pyrethrins | F25: Insecticide | G25: 44362
A26: Y | B26: N/A | C26: Bonide Products, LLC | D26: 67702-54-ZA-4 | E26: Caprylic acid, capric acid | F26: Herbicide, Algaecide | G26: 43958
A27: Y | B27: N/A | C27: Bonide Products, LLC | D27: 67702-59-ZA-4 | E27: Caprylic acid, capric acid | F27: Herbicide, Algaecide | G27: 43843
A28: Y | B28: N/A | C28: Bonide Products, LLC | D28: 67702-54-AA-4 | E28: Caprylic acid, capric acid | F28: Herbicide, Algaecide | G28: 44092
A29: Y | B29: N/A | C29: Bonide Products, LLC | D29: 67702-59-AA-4 | E29: Caprylic acid, capric acid | F29: Herbicide, Algaecide | G29: 42464
A30: Y | B30: N/A | C30: Gowan Company, LLC | D30: 10163-326-AA | E30: Capsicum oleoresin, soybean oil, garlic | F30: Insecticide, Repellent | G30: 44258
A31: Y | B31: N/A | C31: Gowan Company, LLC | D31: 10163-336-AA | E31: Capsicum oleoresin, soybean oil, garlic | F31: Insecticide, Repellent | G31: 43192
A32: Y | B32: N/A | C32: Bioworks, Inc. D/B/A Bioworks | D32: 264-1155-AA-68539 | E32: QST 713 strain of dried Bacillus subtilis | F32: Fungicide | G32: 42760
A33: Y | B33: N/A | C33: Imerys Filtration Minerals, Inc. | D33: 73729-1-AA | E33: Diatomaceous earth | F33: Molluscicide, Insecticide | G33: 44292
A34: Y | B34: N/A | C34: Growth Technology Ltd. | D34: 79664-1-AA | E34: IBA (indole-3-butyric acid) | F34: Growth Regulator | G34: 42837
A35: Y | B35: This product can only be applied in greenhouses. | C35: Agro Logistic Systems, Inc. | D35: 70310-7-AA | E35: Margosa oil, azadirachtin | F35: Fungicide, Miticide, Insecticide, Nematicide, Repellent, Growth Regulator | G35: 44357
A36: Y | B36: This product can only be applied in greenhouses. | C36: McLaughlin Gormley King Company, D/B/A MGK | D36: 1021-2876-AA | E36: Margosa oil, azadirachtin | F36: Fungicide, Miticide, Insecticide, Repellent, Nematicide | G36: 44197
... A54: Y | B54: N/A | C54: Verdesian Life Sciences, U.S., LLC, D/B/A/ Verdesian Life Sciences | D54: 73771-5-AA | E54: Potassium phosphite | F54: Fungicide | G54: 44062
A55: Y | C55: Safer, Inc. A Wholly Owned Subsidiary of Woodstream Corporation | D55: 42697-37-ZE | E55: Sulfur | F55: Fungicide, Antimicrobial | G55: 42950
A56: Y | B56: This product can only be applied in greenhouses and nurseries. | C56: Hawthorne Hydroponics LLC D/B/A General Hydroponics | D56: 91865-3-AA | E56: Bacillus velezensis strain: D747 | F56: Bactericide, Fungicide, Antimicrobial | G56: 44083
A57: Y | B57: N/A | C57: Valent Biosciences LLC | D57: 73049-56-ZB | E57: Bacillus thuringiensis subsp. israelensis strain: AM 65-52 | F57: Insecticide | G57: 44097
A58: Y | C58: Vallent Biosciences, LLC | D58: 73049-56-ZB | E58: Bacillus thuringiensis subsp. strain: AM 65-52 | F58: Fungicide | G58: 40757
A59: Y | B59: N/A | C59: Pro Farm Group, Inc. | D59: 84059-27-ZA | E59: Chromobacterium subtsugae strain: PRAA 4-1 | F59: Miticide, Insecticide | G59: 44077
A60: Y | B60: This product is an adjuvant. It can be used with other registered products that meet the legal criteria for use on cannabis, but not independently. | C60: Grow More, Inc. | D60: 70908-50001-AA | E60: Polyethoxylated nonylphenol | F60: Adjuvant | G60: 44062
A61: Y | B61: This product can only be applied around the crop but not to it. | C61: P.F. Harris Manufacturing Company, LLC | D61: 85208-1-AA-3 | E61: Acetic acid | F61: Herbicide | G61: 44062
A62: Y | B62: N/A | C62: Certis USA, LLC | D62: 67702-54-AA-70051 | E62: Caprylic acid, capric acid | F62: Herbicide, Desiccant, Algaecide | G62: 45427
A63: Y | B63: N/A | C63: Maia Products Inc./Ag Division | D63: 8281-2-ZA | E63: IBA (indole-3-butyric acid) | F63: Growth Regulator | G63: 43699
A64: Y | B64: This product has several restrictions on how it can be applied. The user must follow the label directions carefully. | C64: Hortus USA Corporation | D64: 63310-22-AA | E64: IBA (indole-3-butyric acid) | F64: Growth Regulator | G64: 44299
A65: Y | B65: This product can only be used indoor on cannabis related structures (e.g. flooring, crevices, etc.). It cannot be applied to the cannabis plant. | C65: St. Gabriel Organics, LLC | D65: 63191-17-ZA | E65: Diatomaceous earth | F65: Insecticide | G65: 41382
A66: Y | B66: N/A | C66: Belchim Crop Production Us Corporation | D66: 67702-32-ZA-87865 | E66: Ferric sodium EDTA | F66: Molluscicide | G66: 42353
A67: Y | B67: Updated label - no restrictions or exceptions. Older container labels may restrict product to applications in greenhouses and to cannabis grown for seed. | C67: Koppert Biological Systems, Inc. | D67: 89635-5-AA | E67: Isaria funosorosea strain: FE 9901 | F67: Insecticide | G67: 45895
A68: Y | B68: This product can be used as a pre-plant dip treatment on cannabis seeds, seedlings, or cuttings, as a soil drench, and for bare-root nursery stock. It cannot be applied as a foliar spray in greenhouses or in the field, nor can it be applied to a growing crop. | C68: Pro Farm Group, Inc. | D68: 84059-32-AA | E68: Peroxyacetic acid, hydrogen peroxide | F68: Bactericide, Fungicide, Algaecide, Antimicrobial, Slimicide | G68: 44728
A69: Y | B69: This product is an adjuvant. It can be used with other registered products that meet the legal criteria for use on cannabis, but not independently. | C69: Helena Agri-Enterprises LLC D/B/A Helena Chemical Company | D69: 5905-50087-AA | E69: N/A | F69: Adjuvant | G69: 43483
A70: Y | B70: N/A | C70: Danstar Ferment Ag / Lallemand Plant Care | D70: 64137-13-AA | E70: Clonostachys rosea strain: J1446 | F70: Fungicide | G70: 44299
... A91: Y | B91: This product is an adjuvant. It can be used with other registered products that meet the legal criteria for use on cannabis, but not independently. | C91: Oro Agri, Inc. | D91: 72662-50005-AA | E91: N/A | F91: Adjuvant | G91: 45358
A92: Y | C92: Biosafe Systems, LLC | D92: 70299-12-ZA | E92: Hydrogen peroxide, peroxyacetic acid | F92: Bactericide, Fungicide, Algaecide, Antimicrobial | G92: 45026
A93: Y | B93: N/A | C93: Biosafe Systems, LLC | D93: 70299-28-AA | E93: Hydrogen peroxide, peroxyacetic acid | F93: Bactericide, Fungicide, Algaecide, Antimicrobial | G93: 42628
A94: Y | B94: N/A | C94: Biosafe Systems, LLC | D94: 70299-22-AA | E94: Hydrogen peroxide, potassium phosphite | F94: Bactericide, Fungicide | G94: 44879
A95: Y | B95: This product can only be used in cannabis related water processing systems. | C95: Envir Tech Chemical Services, Inc. | D95: 63838-2-ZB | E95: Hydrogen peroxide, peroxyacetic acid | F95: Bactericide, Fungicide, Algaecide, Antimicrobial, Slimicide | G95: 42320
A96: Y | B96: This product can only be used for soil, seed treatments, and dip treatments. | C96: Enviro Tech Chemical Services, Inc. | D96: 63838-1-ZB | E96: Hydrogen peroxide, peroxyacetic acid | F96: Bactericide, Fungicide, Algaecide, Antimicrobial, Slimicide | G96: 44091
A97: Y | C97: BioSafe Systems, LLC | D97: 70299-15-ZA | E97: Sodium percarbonate | F97: Bactericide, Fungicide, Antimicrobial | G97: 43818
A98: Y | B98: N/A | C98: Perma-Guard, Inc. | D98: 73729-1-AA-67197 | E98: Diatomaceous earth | F98: Desiccant, Insecticide | G98: 44091
A99: Y | B99: N/A | C99: Certis USA, LLC | D99: 70051-19-ZA | E99: Paecilomyces fumosoroseus apopka strain: 97 | F99: Insecticide | G99: 44105
A100: Y | B100: This product can only be used in recirculating hydroponic systems. | C100: Arborjet, Inc | D100: 74578-3-AA | E100: Potassium phosphite | F100: Fungicide | G100: 42108
A101: Y | B101: N/A | C101: Vivid Life Sciences, LLC | D101: 87663-11-AA-92697 | E101: Ammonium nonanoate | F101: Herbicide, Algaecide | G101: 42620
A102: Y | B102: N/A | C102: Premier Tech Growers and Consumers Inc. | D102: 74267-4-ZE | E102: Bacillus pumilus strain: GHA 180 | F102: Fungicide, Insecticide | G102: 44354
A103: Y | B103: N/A | C103: Premier Tech Growers and Consumers Inc. | D103: 74267-4-ZD | E103: Bacillus pumilus strain: GHA 180 | F103: Fungicide, Insecticide | G103: 41821
A104: Y | B104: N/A | C104: Premier Tech Growers and Consumers Inc. | D104: 74267-4-ZC | E104: Bacillus pumilus strain: GHA 180 | F104: Fungicide, Insecticide | G104: 42662
A105: Y | B105: N/A | C105: Premier Tech Growers and Consumers Inc. | D105: 74267-4-AA | E105: Bacillus pumilus strain: GHA 180 | F105: Fungicide, Insecticide | G105: 42234
A106: Y | B106: N/A | C106: Premier Tech Growers and Consumers Inc. | D106: 74267-4-ZA | E106: Bacillus pumilus strain: GHA 180 | F106: Fungicide, Insecticide | G106: 43952
A107: Y | B107: N/A | C107: Premier Tech Growers and Consumers Inc. | D107: 74267-4-ZB | E107: Bacillus pumilus strain: GHA 180 | F107: Fungicide, Insecticide | G107: 42873
A108: Y | B108: N/A | C108: McLaughlin Gormley King Company, D/B/A MGK | D108: 1021-1771-AA | E108: Pyrethrins | F108: Insecticide | G108: 43643
A109: Y | B109: N/A | C109: McLaughlin Gormley King Company, D/B/A MGK | D109: 1021-1772-AA | E109: Pyrethrins | F109: Insecticide | G109: 44376
... A128: Y | B128: N/A | C128: Pro Farm Group, Inc. | D128: 84059-14-ZC | E128: Burkholderia rinojensis strain: A398 | F128: Miticide, Insecticide | G128: 43503
A129: Y | C129: Pro Farm Group, Inc. | D129: 84059-14-ZA | E129: Burkholderia rinojensis strain: A397 | F129: Insecticide, Nematicide | G129: 44202
A130: y | B130: N/A | C130: Energen Carolina, LLC | D130: 85208-1-AA-92429 | E130: Acetic acid | F130: Herbicide | G130: 42513
A131: Y | B131: N/A | C131: This Land Inc., D/B/A Sunday | D131: 67702-34-AA-93737 | E131: Ammonium soaps of fatty acids | F131: Herbicide, Algaecide | G131: 44449
A132: Y | B132: This product can only be applied in greenhouses, shadehouses, and outdoor nurseries. | C132: Valent Biosciences LLC | D132: 73049-40-AA | E132: Bacillus thuringiensis subsp. aizawai strain: ABTS-1857 | F132: Insecticide | G132: 41352
A133: Y | B133: N/A | C133: Biosafe Systems, LLC | D133: 70299-12-AA | E133: Hydrogen peroxide, peroxyacetic acid | F133: Bactericide, Fungicide, Algaecide, Antimicrobial, Slimicide | G133: 43990
A134: Y | B134: N/A | C134: Biosafe Systems, LLC | D134: 70299-16-ZD | E134: Hydrogen peroxide, peroxyacetic acid | F134: Bactericide, Fungicide, Algaecide, Antimicrobial | G134: 43663
A135: N | B135: N/A | C135: Safer, Inc., A Wholly-Owned Subsidary of Woodstream Corporation | D135: 59913-13-ZA | E135: Potassium laurate, sulfur | F135: Insecticide | G135: 44287
A136: N | B136: N/A | C136: Safer, Inc., A Wholly-Owned Subsidary of Woodstream Corporation | D136: 59913-12-ZD | E136: Potassium laurate, sulfur | F136: Fungicide, Miticide, Insecticide | G136: 44169
A137: N | B137: N/A | C137: Lawn And Garden Products, Inc. | D137: 70051-2-AA-54705 | E137: Clarified hydrophobic extract of neem oil | F137: Fungicide, Miticide, Insecticide | G137: 42724
A138: N | B138: N/A | C138: Novozymes BioAg, Inc. | D138: 73314-1-ZD | E138: Strepomyces lydicus strain: WYEC 108 | F138: Fungicide, Antimicrobial | G138: 42724
A139: N | B139: N/A | C139: Certis USA, LLC | D139: 70051-47-ZC | E139: Bacillus thuringiensis subsp. aizawai | F139: Insecticide | G139: 44775
A140: N | B140: N/A | C140: Nichino America, Inc. | D140: 71711-4-AA | E140: Fenproximate | F140: Miticide, Insecticide | G140: 42780
A141: N | B141: N/A | C141: Nufarm Americas, Inc. Agt Division | D141: 55146-83-ZA | E141: Mono- and di-basic sodium, potassium, and ammonium salts of phosphorus acid | F141: Fungicide | G141: 40757
... A144: N | B144: N/A | C144: Biobest USA, Inc. | D144: 87301-1-AA-91594 | E144: Trichoderma asperellum strain: T-34 | F144: Fungicide | G144: 42928
A145: N | C145: UPL NA Inc. | D145: 8033-36-AA-70506 | E145: Acetamiprid | F145: Insecticide | G145: 44419
A146: N | B146: N/A | C146: McLaughlin Gormley King Company, D/B/A MGK | D146: 1021-1872-ZA | E146: Azadirachtin, pyrethrins | F146: Insecticide | G146: 33125
A147: N | B147: N/A | C147: Vallent Biosciences, LLC | D147: 73049-452-AA | E147: Bacillus thuringiensis subsp. israelensis strain: AM 65-52 | F147: Insecticide | G147: 44098
A148: N | C148: Valent U.S.A. LLC | D148: 59639-150-AA | E148: Clothianidin | F148: Insecticide | G148: 44551
A149: N | B149: N/A | C149: Plant Health Intermediate Inc. D/B/A DPH Biologicals | D149: 94485-5-AA | E149: Bacillus velezensis strain: GB03 | F149: Growth Regulator, Bactericide, Fungicide, Antimicrobial | G149: 45365
A150: N | B150: N/A | C150: Anatis BioProtection, Inc. | D150: 89600-7 | E150: Beauveria bassiana | F150: Insecticide | G150: Not registered in CA
A151: N | B151: N/A | C151: Anatis BioProtection, Inc. | D151: 89600-2-AA | E151: Beauveria bassiana | F151: Insecticide | G151: 45565
A152: N | B152: N/A | C152: Isagro S.P.A., D/B/A Isagro USA Inc. | D152: 80289-9-ZA | E152: Trichoderma asperellum strain: Icc 012, Trichoderma gamsii strain: ICC 080 | F152: Fungicide | G152: 41397
A153: N | C153: Corteva Agriscience, LLC | D153: 62719-523 | E153: Spinosad | F153: Insecticide | G153: Not registered in CA
A154: N | B154: N/A | C154: Bonide Products, LLC | D154: 4-80-ZE | E154: Mineral oil | F154: Insecticide, Fungicide | G154: 43236
A155: N | B155: N/A | C155: Bonide Products, LLC | D155: 4-80-ZC | E155: Mineral oil | F155: Insecticide, Fungicide | G155: 44614
A156: N | B156: N/A | C156: Bonide Products, LLC | D156: 4-431-AA | E156: IBA (indole-3-butyric acid) | F156: Plant Growth Regulator, Growth Stimulator | G156: 41003
A157: N | B157: N/A | C157: Bonide Products, LLC | D157: 67702-13-ZD-4 | E157: Potassium salts of fatty acids | F157: Insecticide | G157: 41228
A158: N | B158: N/A | C158: Bonide Products, LLC | D158: 70051-2-ZD-4 | E158: Clarified hydrophobic extract of neem oil | F158: Insecticide, Fungicide, Miticide | G158: 43873
A159: N | B159: N/A | C159: Bonide Products, LLC | D159: 70051-13-ZG-4 | E159: Clarified hydrophobic extract of neem oil | F159: Insecticide, Fungicide, Miticide | G159: 43997
A160: N | B160: N/A | C160: Bonide Products, LLC | D160: 70051-74-ZA-4 | E160: Clarified hydrophobic extract of neem oil, piperonyl butoxide, pyrethrins | F160: Fungicide, Miticide, Insecticide | G160: 43119
A161: N | B161: N/A | C161: Certis USA, LLC | D161: 82074-2-AA | E161: Beauveria bassiana strain: GHA | F161: Insecticide | G161: 43615
A162: N | B162: N/A | C162: Certis USA, LLC | D162: 82074-1-AA | E162: Beauveria bassiana strain: GHA | F162: Insecticide | G162: 44823
A163: N | B163: N/A | C163: Certis USA, LLC | D163: 82074-17-ZA | E163: Beauveria bassiana strain: GHA | F163: Insecticide | G163: 45232
...

Sheet Colorado Allowables
A1: Colorado product name | B1: Company name | C1: EPA Number | D1: Commercial | E1: Home | F1: Hemp | G1: Public Comments | H1: Type | I1: Ingredient1_name | J1: Percent1 | K1: Ingredient2_name | L1: Percent2 | M1: Ingredient3_name | N1: Percent3 | O1: Ingredient4_name | P1: Percent4 | Q1: Ingredient5_name | R1: Percent5 | S1: Ingredient6_name | T1: Percent6 | U1: Ingredient7_name | V1: Percent7
A2: 70% Neem Oil (Monterey) | B2: Lawn and Garden Products, Inc | C2: 70051-2-54705 | D2: No | E2: Yes | F2: No | H2: Fungicide, Insecticide | I2: Clarified Hydrophobic Extract of Neem Oil | J2: 70.000%
A3: AGP4 | B3: AGP4 Advanced Growth & Protection 4 Formula | C3: 0-0-0 | D3: Yes | E3: Yes | F3: Yes | H3: Fungicide, Insecticide | I3: Soybean Oil | J3: 10.000% | K3: Corn Oil | L3: 5.000%
A4: Agree WG | B4: Certis USA, LLC | C4: 70051-47 | D4: Yes | E4: Yes | F4: Yes | G4: Hemp added to label 9-2021 | H4: Insecticide | I4: Bacillus thuringiensis SSP. Aizawai | J4: 50.000%
A5: Agro Pest | B5: Agro Research International LLC | C5: 25(b) | D5: Yes | E5: Yes | F5: Yes | H5: Insecticide | I5: Thyme oil | J5: 13.000% | K5: Rosemary Oil | L5: 10.000%
A6: All Phase | B6: Circadian Crop Sciences LLC | C6: 25(b) | D6: Yes | E6: Yes | F6: Yes | H6: fungicide, bactericide | I6: Potassium Sorbate | J6: 34.700% | K6: Sodium Lauryl Sulfate | L6: 2.000%
A7: AlliCURB MAX | B7: Kemin Industries, Inc. | C7: 0-0-0 | D7: Yes | E7: No | F7: Yes | G7: Commerical Use Only | H7: Insecticide | I7: Castor Oil | J7: 27.000% | K7: Garlic Oil | L7: 8.000%
A8: Almighty | B8: Gropro | C8: 25(b) | D8: Yes | E8: Yes | F8: Yes | H8: nematicide | I8: Geraniol | J8: 4.500%
A9: Ancora | B9: OHP, Inc. | C9: 70051-19-59807 | D9: Yes | E9: Yes | F9: Yes | G9: Hemp on label | H9: Insecticide, Fungicide | I9: Isaria fumosorosea | J9: 20.000%
A10: Athena IPM | B10: Athena Ag, Inc. | C10: 0-0-0 | D10: Yes | E10: Yes | F10: Yes | G10: NEW FORMULA! Check the label! This is the only Athena IPM permitted on cannabis. | H10: Insecticide | I10: Peppermint Oil | J10: 0.250% | K10: Cinnamon Oil | L10: 0.250% | M10: Citric Acid | N10: 0.220%
A11: Atrevia 3.0% SL | B11: Atticus, LLC | C11: 91234-305 | D11: Yes | E11: Yes | F11: Yes | H11: Insecticide | I11: Azadirachtin | J11: 3.000%
A12: Axxe Broad Spectrum Herbicide | B12: BioSafe Systems, LLC | C12: 70299-23 | D12: Yes | E12: Yes | F12: Yes | G12: Greenhouse Use Only. | H12: Herbicide | I12: Ammonium Nonanoate | J12: 40.000%
A13: Aza-Direct Biological Insecticide | B13: Gowan Company | C13: 71908-1-10163 | D13: Yes | E13: Yes | F13: Yes | H13: Insecticide | I13: Azadirachtin | J13: 1.200%
A14: AzaGuard | B14: BioSafe Systems, LLC | C14: 70299-17 | D14: Yes | E14: Yes | F14: Yes | H14: Insecticide | I14: Azadirachtin | J14: 3.000%
A15: AzaMax | B15: Parry America | C15: 71908-1-81268 | D15: Yes | E15: Yes | F15: Yes | G15: hemp added to label 5-2020 | H15: Insecticide, Nematicide | I15: Azadirachtin | J15: 1.200%
A16: AzaSol | B16: Arborjet, Inc. | C16: 81899-4-74578 | D16: Yes | E16: Yes | F16: Yes | H16: Insecticide | I16: Azadirachtin | J16: 6.000%
A17: Azasol WSP | B17: Arborjet Inc. | C17: 81899-4-74578 | D17: Yes | E17: Yes | F17: Yes | H17: Insecticide | I17: Azadirachtin | J17: 6.000%
A18: Azatin O Biological Insecticide | B18: OHP, Inc. | C18: 70051-9-59807 | D18: Yes | E18: Yes | F18: Yes | H18: IGR | I18: Azadirachtin | J18: 4.500%
A19: Azera Gardening | B19: Mclaughlin Gormley King dba MGK | C19: 1021-1872 | D19: No | E19: Yes | F19: No | H19: Insecticide | I19: Azadirachtin | J19: 1.200% | K19: Pyrethrins | L19: 1.400%
A20: Azera Insecticide | B20: McLaughlin Gormley King Company dba MGK | C20: 1021-1872 | D20: Yes | E20: Yes | F20: Yes | H20: Insecticide, Miticide, Fungicide | I20: Azadirachtin | J20: 1.200% | K20: Pyrethrins | L20: 1.400%
A21: Azera Pro | B21: McLaughlin Gormley King Company dba MGK | C21: 1021-1872 | D21: Yes | E21: Yes | F21: Yes | G21: Greenhouse use only | H21: Insecticide | I21: Pyrethrins | J21: 1.400% | K21: Azadirachtin | L21: 1.200%
A22: Bacilirid Biological Fungicide | B22: Koppert Biological Systems, Inc. | C22: 71840-8-89635 | D22: Yes | E22: Yes | F22: Yes | H22: Fungicide | I22: Bacillus subtilis MBI 600 | J22: 11.000%
A23: BellaTrove Companion Maxx WP | B23: DPH Biologicals LLC | C23: 94485-5 | D23: Yes | E23: Yes | F23: Yes | H23: fungicide, bactericide | I23: Bacillus amyloliquefaciens strain ENV503 | J23: 0.149%
A24: Beloukha Garden Herbicide | B24: Certis Belchim B.V. | C24: 91746-8 | D24: Yes | E24: Yes | F24: Yes | H24: Herbicide | I24: Pelargonic Acid | J24: 51.980%
A25: BioCeres EC | B25: Anatis Bioprotection Inc. | C25: 89600-4 | D25: Yes | E25: No | F25: Yes | G25: Hemp on Label | H25: Insecticide | I25: Beauveria bassiana strain ANT-03 | J25: 10.000%
A26: Bioceres GR | B26: Anatis Bioprotection Inc. | C26: 89600-7 | D26: Yes | E26: Yes | F26: Yes | G26: Hemp on label | H26: Insecticide | I26: Beauveria bassiana strain ANT-03 | J26: 7.000%
A27: BioCeres WP | B27: Anatis Bioprotection Inc | C27: 89600-2 | D27: Yes | E27: Yes | F27: Yes | G27: Hemp added to label 5-28-2020. | H27: Insecticide | I27: Beauveria bassiana strain ANT-03 | J27: 20.000%
A28: BioSafe Weed & Grass Killer | B28: BioSafe Systems LLC | C28: 70299-25 | D28: Yes | E28: Yes | F28: Yes | G28: Contact herbicide, will damage all treated leaves | H28: herbicide | I28: Ammonium Nonanoate | J28: 40.000%
A29: BluOX 34 | B29: Clean Chemistry | C29: 92013-5 | D29: Yes | E29: Yes | F29: Yes | H29: Fungicide | I29: Hydrogen Peroxide | J29: 34.500%
A30: BotaniGard 22WP | B30: Certis USA, LLC | C30: 82074-2 | D30: Yes | E30: Yes | F30: Yes | G30: Hemp added to label september 2020 | H30: Insecticide | I30: Beauveria bassiana Strain GHA | J30: 22.000%
A31: BotaniGard ES | B31: Certis USA, LLC | C31: 82074-1 | D31: Yes | E31: Yes | F31: Yes | G31: Hemp added to label September, 2020. | H31: insecticide | I31: Beauveria bassiana Strain GHA | J31: 11.300%
A32: Botanigard Maxx | B32: Certis USA, LLC | C32: 82074-5 | D32: Yes | E32: Yes | F32: Yes | H32: Insecticide | I32: Pyrethrins | J32: 0.750% | K32: Beauveria bassiana Strain GHA | L32: 0.060%
A33: BotaniGard Optima ES | B33: Certis USA, LLC | C33: 82074-17 | D33: Yes | E33: Yes | F33: Yes | H33: Insecticide | I33: Beauveria bassiana Strain GHA | J33: 2.000%
A34: BoteGHA ES | B34: Certis USA, LLC | C34: 82074-1 | D34: Yes | E34: Yes | F34: Yes | G34: Hemp on label | H34: Insecticide | I34: Beauveria bassiana Strain GHA | J34: 11.300%
A35: BoteGHA Optima ES | B35: Certis USA, LLC | C35: 82074-17 | D35: Yes | E35: Yes | F35: Yes | H35: Insecticide | I35: Beauveria bassiana Strain GHA | J35: 2.000%
A36: BotryStop WP | B36: BioWorks, Inc. | C36: 68539-17 | D36: Yes | E36: Yes | F36: Yes | G36: Hemp on label | H36: Fungicide | I36: Ulocladium oudemansii | J36: 45.000%
A37: Brandt Ecotec Plus | B37: Brandt Consolidated, Inc. | C37: 25(b) | D37: Yes | E37: Yes | F37: Yes | H37: Insecticide, Miticide | I37: Rosemary Oil | J37: 10.000% | K37: Geraniol | L37: 5.000% | M37: Peppermint Oil | N37: 2.000%
A38: BRANDT GroFusion | B38: BRANDT Consolidated, Inc. | C38: 57538-74-48813 | D38: Yes | E38: Yes | F38: Yes | H38: Plant Growth Regulator | I38: Cytokinin (Kinetin) | J38: 0.040%
A39: BRANDT OptiThrive | B39: BRANDT Consolidated, Inc. | C39: 90866-23-48813 | D39: Yes | E39: Yes | F39: Yes | H39: Plant Growth Regulator | I39: Cytokinin (Kinetin) | J39: 0.120% | K39: Gamma Aminobutyric Acid (GABA) | L39: 1.000% | M39: Choline Chloride | N39: 2.000%
A40: Brandt Turfzilla | B40: Brandt Consolidated, Inc. | C40: 83416-1-48813 | D40: Yes | E40: Yes | F40: Yes | G40: only for hydroponics, seed treatment, and greenhouse & nursery bedding plants. | H40: fungicide | I40: Phosphorous Acid, Mono- and Di-Potassium Salts of | J40: 45.800%
A41: BT Now | B41: Biosafe Systems, LLC | C41: 89046-12-70299 | D41: Yes | E41: Yes | F41: Yes | H41: insecticide | I41: Bacillus thuringiensis SSP. Kurstaki | J41: 14.490%
A42: Bug Buster-O | B42: Lawn and Garden Products, Inc | C42: 1021-1771-54705 | D42: Yes | E42: Yes | F42: Yes | G42: Outdoor use only. | H42: Insecticide | I42: Pyrethrins | J42: 1.400%
A43: Canna Control | B43: CANNA Continental | C43: 0-0-0 | D43: Yes | E43: Yes | F43: Yes | H43: Insecticide, Fungicide, Bactericide | I43: Soybean Oil | J43: 60.000% | K43: Thyme oil | L43: 15.000%
A44: Captain Jack's Neem Oil Ready to Use | B44: Bonide Products, LLC | C44: 70051-13-4 | D44: No | E44: Yes | F44: Yes | H44: fungicide, insecticide, miticide | I44: Clarified Hydrophobic Extract of Neem Oil | J44: 0.900%
A45: Captiva | B45: Gowan Company | C45: 10163-326 | D45: Yes | E45: Yes | F45: Yes | H45: Insect Repellent | I45: Capsicum Oleoresin Extract | J45: 7.600% | K45: Garlic Oil | L45: 23.400% | M45: Soybean Oil | N45: 59.300%
A46: Captiva Prime | B46: Gowan Company | C46: 10163-336 | D46: Yes | E46: Yes | F46: Yes | H46: Insecticide | I46: Capsicum Oleoresin Extract | J46: 7.600% | K46: Garlic Oil | L46: 23.400% | M46: Canola Oil | N46: 55.000%
A47: Cease | B47: BioWorks, Inc. | C47: 264-1155-68539 | D47: Yes | E47: Yes | F47: Yes | H47: Fungicide | I47: Bacillus subtilis QST713 Strain | J47: 1.340%
A48: Chester Boone's All Purpose Plant and Garden | B48: Chester Boone's LLC | C48: 0-0-0 | D48: Yes | E48: Yes | F48: Yes | H48: Insecticide, Fungicide, Miticide | I48: Citric Acid | J48: 0.050%
A49: Chester Boone's Pure | B49: Chester Boones LLC | C49: 0-0-0 | D49: Yes | E49: Yes | F49: Yes | H49: Insecticide | I49: Citric Acid | J49: 0.100%
A50: CHS Unlocked PRO | B50: CHS Inc. | C50: 90930-8-48013 | D50: Yes | E50: Yes | F50: Yes | H50: Plant Growth Regulator | I50: Homobrassinolide | J50: 0.003% | K50: Indole-3-butyric acid | L50: 0.010% | M50: Gibberellins (Gibberellic Acid) | N50: 0.009%
A51: Cinnaction | B51: Idai Nature USA Corp. | C51: 25(b) | D51: Yes | E51: Yes | F51: Yes | H51: insecticide, fungicide, miticide, bacericide | I51: Cinnamon Oil | J51: 10.000%
A52: Cinnaction Next | B52: Oro Agri, Inc. | C52: 0-0-0 | D52: Yes | E52: Yes | F52: Yes | H52: Insecticide | I52: Cinnamon Oil | J52: 10.000%
A53: Cinnex | B53: Sym-Agro, Inc. | C53: 87946-1 | D53: Yes | E53: Yes | F53: Yes | H53: fungicide, insecticide | I53: Cinnamaldehyde | J53: 22.500%
A54: Cintro | B54: BioWorks, Inc. | C54: 67702-11-68539 | D54: Yes | E54: Yes | F54: Yes | H54: Insecticide | I54: Potassium Salts of Fatty Acids | J54: 47.000%
A55: Circadian Sunrise | B55: Circadian Crop Sciences, LLC | C55: 25(b) | D55: Yes | E55: Yes | F55: Yes | H55: insecticide, fungicide, miticide | I55: Corn Oil | J55: 17.000% | K55: Peppermint Oil | L55: 10.000%
A56: Clonex Rooting Gel | B56: Growth Technology Ltd. | C56: 79664-1 | D56: Yes | E56: Yes | F56: Yes | H56: PGR | I56: IBA (Indole-3-Butyric Acid) | J56: 0.310%
A57: Companion Maxx Liquid Biologial Fungicide | B57: DPH Biologicals LLC | C57: 94485-4 | D57: Yes | E57: Yes | F57: Yes | G57: Hemp on label | H57: Fungicide | I57: Bacillus amyloliquefaciens strain ENV503 | J57: 0.001%
A58: Consequence | B58: Impello Biosciences, Inc. | C58: 0-0-0 | D58: Yes | E58: Yes | F58: Yes | H58: Fungicide/Nematicide/Bactericide | I58: Chitosan | J58: 5.000%
A59: Corry's Slug & Snail Killer | B59: Matson, LLC | C59: 67702-33-8119 | D59: Yes | E59: Yes | F59: Yes | H59: Molluscicide | I59: Sodium Ferric EDTA | J59: 5.000%
A60: Crop Protect Direct PGP | B60: Jabco, LLC | C60: 90866-13-101458 | D60: Yes | E60: Yes | F60: Yes | G60: Hemp on label | H60: Plant Growth Regulator | I60: IBA (Indole-3-Butyric Acid) | J60: 0.850% | K60: Cytokinin (Kinetin) | L60: 0.150%
A61: Crymax | B61: Certis USA, LLC | C61: 70051-86 | D61: Yes | E61: Yes | F61: Yes | G61: Hemp added to label 7/2020. | H61: Insecticide | I61: Bacillus thuringiensis SSP. Kurstaki | J61: 40.000%
A62: Cueva Fungicide Concentrate | B62: Certis USA, LLC | C62: 67702-2-70051 | D62: No | E62: No | F62: Yes | G62: Special Local Need label allows use on hemp. Cueva product label and SLN CO-200001 label must be in applicator's possession at the time of application. | H62: fungicide | I62: Copper Octanoate | J62: 10.000%
A63: Cuts | B63: Athena Ag, Inc. | C63: 82752-1-93752 | D63: Yes | E63: Yes | F63: Yes | H63: Plant Growth Regulator | I63: Indole-3-butyric acid | J63: 0.350%
A64: Cyclone | B64: SJ Enterprises Pty Ltd | C64: 89385-3 | D64: No | E64: Yes | F64: No | H64: Plant Growth Regulator | I64: IBA (Indole-3-Butyric Acid) | J64: 0.170%
A65: Cygin PRO | B65: CHS Inc. | C65: 90930-8-48013 | D65: Yes | E65: Yes | F65: Yes | H65: Plant Growth Regulator | I65: Homobrassinolide | J65: 0.250% | K65: Indole-3-butyric acid | L65: 0.010% | M65: Gibberellins (Gibberellic Acid) | N65: 0.009%
A66: Cytokin Bioregulator Concentrate | B66: Miller Chemical & Fertilizer LLC | C66: 90930-3 | D66: Yes | E66: Yes | F66: Yes | H66: PGR | I66: Cytokinin (Kinetin) | J66: 0.010%
A67: Cytoplex HMS | B67: Miller Chemical & Fertilizer LLC | C67: 90930-6 | D67: Yes | E67: Yes | F67: Yes | H67: PGR | I67: Cytokinin (Kinetin) | J67: 0.010% | K67: IBA (Indole-3-Butyric Acid) | L67: 0.005% | M67: Gibberellins (Gibberellic Acid) | N67: 0.004%
A68: Debug Turbo | B68: MGK | C68: 1021-2874 | D68: Yes | E68: Yes | F68: Yes | G68: Company Name Change | H68: Insecticide, Miticide, Fungicide | I68: Azadirachtin | J68: 0.700% | K68: Neem Oil, Cold Pressed | L68: 65.800%
A69: Debug-ON | B69: MGK | C69: 1021-2879 | D69: Yes | E69: Yes | F69: Yes | G69: Hemp on label | H69: Insecticide, fungicide | I69: Neem Oil, Cold Pressed | J69: 70.000%
A70: Debug-Optimo | B70: MGK | C70: 1021-2876 | D70: Yes | E70: Yes | F70: Yes | G70: Company Name Change | H70: Insecticide | I70: Azadirachtin | J70: 0.700% | K70: Neem Oil, Cold Pressed | L70: 15.040%
A71: Debug-Tres | B71: MGK | C71: 1021-2877 | D71: Yes | E71: Yes | F71: Yes | G71: New Company Name | H71: Insecticide, Fungicide, Nematicide | I71: Azadirachtin | J71: 3.000% | K71: Neem Oil, Cold Pressed | L71: 4.700%
A72: Deliver Biological Insecticide | B72: Certis USA, LLC | C72: 70051-69 | D72: Yes | E72: Yes | F72: Yes | H72: Insecticide | I72: Bacillus thuringiensis SSP. Kurstaki | J72: 85.000%
A73: DESPOT Snail & Slug Bait | B73: Simplot Turf & Horticulture | C73: 67702-33-95428 | D73: Yes | E73: Yes | F73: Yes | G73: Hemp on label | H73: Mollusicide | I73: Sodium Ferric EDTA | J73: 5.000%
A74: Des-X Insecticidal Soap Concentrate | B74: Certis USA, LLC | C74: 67702-22-70051 | D74: Yes | E74: Yes | F74: Yes | H74: Insecticide | I74: Potassium Laurate | J74: 47.000%
A75: DiPel DF Biological Insecticide | B75: Valent BioSciences LLC | C75: 73049-39 | D75: Yes | E75: Yes | F75: Yes | G75: Greenhouse only. The label lists specific pests in which this product can be used for. | H75: Insecticide | I75: Bacillus thuringiensis SSP. Kurstaki | J75: 54.000%
A76: DiPel PRO DF Biological Insecticide | B76: Valent BioSciences LLC | C76: 73049-39 | D76: Yes | E76: Yes | F76: Yes | G76: The label lists specific pests in which this product can be used for. | H76: Insecticide | I76: Bacillus thuringiensis SSP. Kurstaki | J76: 54.000%
A77: DiTera DF Biological Nematicide Dry Flowable | B77: Valent BioSciences LLC | C77: 73049-67 | D77: Yes | E77: Yes | F77: Yes | H77: Nematicide | I77: Myrothecium verrucaria | J77: 90.000%
A78: Double Nickel LC | B78: Certis USA, LLC | C78: 70051-107 | D78: Yes | E78: Yes | F78: Yes | G78: hemp added to label, plus separate hemp supplemental label | H78: Fungicide | I78: Bacillus amyloliquefaciens Strain D747 D747 | J78: 98.850%
A79: DoubleNickel55 | B79: Certis USA, LLC | C79: 70051-108 | D79: Yes | E79: Yes | F79: Yes | G79: Hemp on label | H79: Fungicide | I79: Bacillus amyloliquefaciens Strain D747 D747 | J79: 25.000%
A80: Dr. Earth Final Stop OMRI Disease Control Fungicide (RTU) | B80: Dr. Earth, Inc. | C80: 25(b) | D80: Yes | E80: Yes | F80: Yes | H80: Fungicide | I80: Rosemary Oil | J80: 0.060% | K80: Clove Oil | L80: 0.050% | M80: Peppermint Oil | N80: 0.050%
A81: Dr. Earth Final Stop OMRI Disease Control Fungicide Concentrate | B81: Dr. Earth, Inc. | C81: 25(b) | D81: Yes | E81: Yes | F81: Yes | H81: Fungicide | I81: Rosemary Oil | J81: 0.900% | K81: Clove Oil | L81: 0.750% | M81: Peppermint Oil | N81: 0.750%
A82: Dr. Earth Final Stop OMRI Fruit Tree Insect Killer (RTU) | B82: Dr. Earth, Inc. | C82: 25(b) | D82: Yes | E82: Yes | F82: Yes | H82: Insecticide | I82: Rosemary Oil | J82: 0.060% | K82: Sesame Oil | L82: 0.050% | M82: Peppermint Oil | N82: 0.040% | O82: Thyme oil | P82: 0.030% | Q82: Cinnamon Oil | R82: 0.030% | S82: Garlic Oil | T82: 0.020%
A83: Dr. Earth Final Stop OMRI Fruit Tree Insect Killer Concentrate | B83: Dr. Earth, Inc. | C83: 25(b) | D83: Yes | E83: Yes | F83: Yes | H83: Insecticide | I83: Rosemary Oil | J83: 0.750% | K83: Sesame Oil | L83: 0.500% | M83: Peppermint Oil | N83: 0.400% | O83: Thyme oil | P83: 0.300% | Q83: Cinnamon Oil | R83: 0.300% | S83: Garlic Oil | T83: 0.300%
A84: Dr. Earth Final Stop OMRI Vegetable Garden Insect Killer (RTU) | B84: Dr. Earth, Inc. | C84: 25(b) | D84: Yes | E84: Yes | F84: Yes | H84: Insecticide | I84: Rosemary Oil | J84: 0.050% | K84: Sesame Oil | L84: 0.050% | M84: Peppermint Oil | N84: 0.040% | O84: Thyme oil | P84: 0.030% | Q84: Cinnamon Oil | R84: 0.030% | S84: Garlic Oil | T84: 0.020%
A85: Dr. Earth Final Stop OMRI Vegetable Garden Insect Killer Concentrate | B85: Dr. Earth, Inc. | C85: 25(b) | D85: Yes | E85: Yes | F85: Yes | H85: Insecticide | I85: Rosemary Oil | J85: 0.750% | K85: Sesame Oil | L85: 0.500% | M85: Peppermint Oil | N85: 0.400% | O85: Thyme oil | P85: 0.300% | Q85: Cinnamon Oil | R85: 0.300% | S85: Garlic Oil | T85: 0.300%
A86: Dr. Earth Final Stop OMRI Weed and Grass Herbicide (RTU) | B86: Dr. Earth, Inc. | C86: 25(b) | D86: Yes | E86: Yes | F86: Yes | H86: Herbicide | I86: Cinnamon Oil | J86: 2.100% | K86: Citric Acid | L86: 2.020% | M86: Clove Oil | N86: 1.500% | O86: Rosemary Oil | P86: 0.040% | Q86: Sesame Oil | R86: 0.040% | S86: Thyme oil | T86: 0.030%
A87: Dr. Earth Final Stop OMRI Yard and Garden Insect Killer (RTU) | B87: Dr. Earth, Inc. | C87: 25(b) | D87: Yes | E87: Yes | F87: Yes | H87: Insecticide | I87: Rosemary Oil | J87: 0.050% | K87: Sesame Oil | L87: 0.050% | M87: Peppermint Oil | N87: 0.040% | O87: Thyme oil | P87: 0.030% | Q87: Cinnamon Oil | R87: 0.030% | S87: Garlic Oil | T87: 0.030%
A88: Dr. Earth Final Stop OMRI Yard and Garden Insect Killer Concentrate | B88: Dr. Earth, Inc. | C88: 25(b) | D88: Yes | E88: Yes | F88: Yes | H88: Insecticide | I88: Rosemary Oil | J88: 0.750% | K88: Sesame Oil | L88: 0.500% | M88: Peppermint Oil | N88: 0.400% | O88: Thyme oil | P88: 0.300% | Q88: Cinnamon Oil | R88: 0.300% | S88: Garlic Oil | T88: 0.300%
A89: Drexel Phiticide | B89: Drexel Chemical Company | C89: 19713-625 | D89: Yes | E89: Yes | F89: Yes | G89: Use allowed prior to final transplant. | H89: Fungicide | I89: Phosphorous Acid, Mono- and Di-Potassium Salts of | J89: 56.200%
A90: DURALEV | B90: SAN Group Biotech USA, Inc. | C90: 91810-2-51517 | D90: Yes | E90: Yes | F90: Yes | H90: fungicide, bactercide | I90: Cerevisane | J90: 94.100%
A91: Earth's Ally 3-IN-1 Plant Spray (RTU) | B91: Sarasota Green Group, LLC | C91: 25(b) | D91: Yes | E91: Yes | F91: Yes | H91: Insecticide, Miticide, Fungicide | I91: Thyme oil | J91: 0.160%
A92: Earth's Ally 3-IN-1 Plant Spray Concentrate | B92: Sarasota Green Group, LLC | C92: 25(b) | D92: Yes | E92: Yes | F92: Yes | H92: Insecticide, Miticide, Fungicide | I92: Thyme oil | J92: 1.860%
A93: Earth's Ally Disease Control (RTU) | B93: Sarasota Green Group | C93: 25(b) | D93: Yes | E93: Yes | F93: Yes | H93: fungicide | I93: Citric Acid | J93: 0.020%
A94: Eco-1 40 | B94: Arborjet, Inc. | C94: 25(b) | D94: Yes | E94: Yes | F94: Yes | H94: insecticide, miticide, fungicide | I94: Linseed Oil | J94: 31.000% | K94: Rosemary Oil | L94: 8.000% | M94: Thyme oil | N94: 1.000%
A95: Eco-1 aza Botanical Insecticide | B95: Arborjet, Inc. | C95: 74578-13 | D95: Yes | E95: Yes | F95: Yes | H95: Insecticide, IGR | I95: Azadirachtin | J95: 6.000%
A96: Eco-1 Fruit & Vegetable Spray | B96: Arborject, Inc. | C96: 25(b) | D96: Yes | E96: Yes | F96: Yes | H96: Insecticide, Miticide, Fungicide | I96: Linseed Oil | J96: 1.000% | K96: Rosemary Oil | L96: 0.100% | M96: Thyme oil | N96: 0.050% | O96: Peppermint Oil | P96: 0.050%
A97: Eco-1 Fruit & Vegetable Spray Concentrate | B97: Arborjet Inc. | C97: 25(b) | D97: Yes | E97: Yes | F97: Yes | H97: Insecticide, Miticide, Fungicide | I97: Linseed Oil | J97: 10.000% | K97: Rosemary Oil | L97: 1.000% | M97: Thyme oil | N97: 0.500% | O97: Peppermint Oil | P97: 0.500%
A98: Eco-1 Garden Spray | B98: Arborjet, Inc. | C98: 25(b) | D98: Yes | E98: Yes | F98: Yes | H98: Insecticide, Miticide, Fungicide | I98: Linseed Oil | J98: 1.000% | K98: Thyme oil | L98: 0.130% | M98: Peppermint Oil | N98: 0.060%
A99: Eco-1 Garden Spray Concentrate | B99: Arborjet, Inc. | C99: 25(b) | D99: Yes | E99: Yes | F99: Yes | H99: Insecticide, Fungicide | I99: Linseed Oil | J99: 10.000% | K99: Thyme oil | L99: 1.340% | M99: Peppermint Oil | N99: 0.660%
A100: EcoGarden | B100: Parry America Inc. | C100: 71908-1-81268 | D100: Yes | E100: Yes | F100: Yes | G100: Hemp added to label 5-2020 | H100: Insecticide, Miticide, Nematicide | I100: Azadirachtin | J100: 1.200%
...

Sheet MSO
A1: Brand | B1: Associated Brand
A2: Curaleaf | B2: Curaleaf
A3: Green Thumb, Inc (GTI)
A4: Trulieve | B4: Trulieve
A5: Verano | B5: Verano
A6: Cresco | B6: Cresco
A7: Curaleaf | B7: Select
A8: Green Thumb, Inc (GTI) | B8: Rise
A9: Trulieve | B9: Zen Leaf
A10: Verano | B10: Verano
A11: Cresco | B11: Sunnyside
A12: Curaleaf | B12: Select
A13: Green Thumb, Inc (GTI) | B13: RYTHM
A14: Green Thumb, Inc (GTI) | B14: Dogwalkers
A15: Green Thumb, Inc (GTI) | B15: Incredibles
... A60: Wana | B60: Wana

Sheet Heavy Metals
A1: Reason | B1: Heavy Metal
A2: Adulterated: Heavy Metal Contamination (Arsenic) | B2: Arsenic
A3: Arsenic | B3: Arsenic
A4: Cadmium | B4: Cadmium
A5: Cadmium | B5: Cadmium
A6: Cadmium, Arsenic | B6: Cadmium
A7: Cadmium, Arsenic | B7: Arsenic
A8: elemental impurities. | B8: Unspecified Heavy Metals
A9: Lead | B9: Lead
A10: Lead Contamination | B10: Lead
A11: Mercury | B11: Mercury
A12: Mercury | B12: Mercury
... A25: Yeast and Mold, Microbials, Arsenic | B25: Arsenic

Sheet ID To Products
A1: Date | B1: State | C1: Doc Link | D1: Type | E1: ID | F1: Company / Producer | G1: Cultivator | I1: Product | J1: Notes
A2: 43675 | B2: Ohio | C2: https://medicalmarijuana.ohio.gov/documents/recalls/recall%20notices%20and%20summaries/archived%20recall%20notices/archived%20recall%20notices.pdf | D2: Voluntary | E2: 43675OhioStandard Wellness | F2: Standard Wellness | H2: M00000021820
H3: M00000028304
A7: 43788 | B7: Ohio | C7: https://medicalmarijuana.ohio.gov/Documents/PatientsCaregivers/One%20Orijin%20Rosin%20Product.pdf | D7: Mandatory | E7: 43788OhioOne Orijin | F7: One Orijin
A8: 43819 | B8: Ohio | C8: https://medicalmarijuana.ohio.gov/documents/recalls/recall%20notices%20and%20summaries/archived%20recall%20notices/archived%20recall%20notices.pdf | D8: Mandatory | E8: 43819OhioGalenas | F8: Galenas | G8: Galenas | H8: M00000034992 | I8: Purple Bomb
G9: Galenas | H9: M00000034991: | I9: Purple Bomb
G10: Galenas | H10: M00000034992 | I10: Purple Bomb
G11: Galenas | H11: M00000034991 | I11: Purple Bomb
G12: Galenas | H12: M00000034985 | I12: THE Organic Strawberry University
A16: 43537 | B16: Ohio | C16: https://medicalmarijuana.ohio.gov/documents/recalls/recall%20notices%20and%20summaries/archived%20recall%20notices/archived%20recall%20notices.pdf | D16: Mandatory | E16: 43537OhioPure Ohio Wellness | F16: Pure Ohio Wellness
A17: 43540 | B17: Ohio | C17: https://medicalmarijuana.ohio.gov/documents/recalls/recall%20notices%20and%20summaries/archived%20recall%20notices/archived%20recall%20notices.pdf | D17: Mandatory | E17: 43540OhioGTI Ohio | F17: GTI Ohio
A18: 44420 | B18: Ohio | C18: https://medicalmarijuana.ohio.gov/documents/recalls/recall%20notices%20and%20summaries/archived%20recall%20notices/archived%20recall%20notices.pdf | D18: Mandatory | E18: 44420OhioBeneleaves Limited | F18: Beneleaves Limited
A19: 44106 | B19: Ohio | C19: https://medicalmarijuana.ohio.gov/documents/recalls/recall%20notices%20and%20summaries/archived%20recall%20notices/archived%20recall%20notices.pdf | D19: Mandatory | E19: 44106OhioVerano Brands | F19: Verano Brands
A20: 44105 | B20: Ohio | C20: https://medicalmarijuana.ohio.gov/documents/recalls/recall%20notices%20and%20summaries/archived%20recall%20notices/archived%20recall%20notices.pdf | D20: Mandatory | E20: 44105OhioVerano Brands | F20: Verano Brands
A21: 44482 | B21: Ohio | C21: https://medicalmarijuana.ohio.gov/documents/recalls/recall%20notices%20and%20summaries/archived%20recall%20notices/archived%20recall%20notices.pdf | D21: Mandatory | E21: 44482OhioCertified Cultivators | F21: Certified Cultivators
A22: 44536 | B22: Ohio | C22: https://medicalmarijuana.ohio.gov/documents/recalls/recall%20notices%20and%20summaries/archived%20recall%20notices/archived%20recall%20notices.pdf | D22: Mandatory | E22: 44536OhioGalenas | F22: Galenas
A23: 44536 | B23: Ohio | C23: https://medicalmarijuana.ohio.gov/documents/recalls/recall%20notices%20and%20summaries/archived%20recall%20notices/archived%20recall%20notices.pdf | D23: Voluntary | E23: 44536OhioGreen Investment Partners, LLC | F23: Green Investment Partners, LLC
A24: 42140 | B24: Maine | C24: https://www.centralmaine.com/2015/09/05/wellness-connection-of-maine-recalls-two-strains-of-medical-marijuana/ | D24: Voluntary | E24: 42140MaineWellness Connection of Maine | F24: Wellness Connection of Maine
A25: 42417 | B25: Colorado | C25: https://sbg.colorado.gov/sites/sbg/files/MED%20Levity%20Advisory%2002192016_1_1.pdf | D25: Mandatory | E25: 42417ColoradoHigh Mountain Medz LLC | F25: High Mountain Medz LLC | H25: Off-Label Pesticides, Myclobutanil and Imidacloprid,
A26: 42417 | B26: Colorado | C26: https://sbg.colorado.gov/sites/sbg/files/MED%20Dr.%20Releaf%20Advisory%2002192016_1_1.pdf | D26: Mandatory | E26: 42417ColoradoDr Releaf Inc | F26: Dr Releaf Inc
A27: 42423 | B27: Colorado | C27: https://sbg.colorado.gov/sites/sbg/files/2.23.16%20XG%20Platinum%20HSA_1_1.pdf | D27: Mandatory | E27: 42423ColoradoXG Platinum Corporation | F27: XG Platinum Corporation
A28: 42424 | B28: Colorado | C28: https://sbg.colorado.gov/sites/sbg/files/Health%20%26%20Safety%20Advisory%20-%20RMO%202-24-16%20Final_1_1.pdf | D28: Mandatory | E28: 42424ColoradoRocky Mountain Organic Medicine Inc | F28: Rocky Mountain Organic Medicine Inc
A29: 42425 | B29: Colorado | C29: https://sbg.colorado.gov/sites/sbg/files/2.25.16%20BTTG%20final_1_1.pdf | D29: Mandatory | E29: 42425ColoradoBack to the Garden Health & Wellness Center LLC | F29: Back to the Garden Health & Wellness Center LLC
A30: 42436 | B30: Colorado | C30: https://sbg.colorado.gov/sites/sbg/files/160307%20Advisory%20-%20Sunrise%20Solutions_Final%20%281%29_2_1.pdf | D30: Mandatory | E30: 42436ColoradoSunrise Solutions LLC | F30: Sunrise Solutions LLC
A31: 42438 | B31: Colorado | C31: https://sbg.colorado.gov/sites/sbg/files/CNW%20Final%2003092016_1.pdf | D31: Mandatory | E31: 42438ColoradoArtisanal Medicinals. | F31: Artisanal Medicinals.
A32: 42439 | B32: Colorado | C32: https://sbg.colorado.gov/sites/sbg/files/Headquarters%20Emp%20HSA%20final%2003102016_1_1.pdf | D32: Mandatory | E32: 42439ColoradoHeadquarters Emporium and Dispensary LLC | F32: Headquarters Emporium and Dispensary LLC
A33: 42439 | B33: Colorado | C33: https://sbg.colorado.gov/sites/sbg/files/SkinnyPineapple%20Final%2003102016_1_1.pdf | D33: Mandatory | E33: 42439ColoradoSkinny Pineapple Inc | F33: Skinny Pineapple Inc
A34: 42443 | B34: Colorado | C34: https://sbg.colorado.gov/sites/sbg/files/AMA%20Final%2003142016_1_1.pdf | D34: Mandatory | E34: 42443ColoradoAdvanced Medical Alternatives LLC | F34: Advanced Medical Alternatives LLC
A35: 42443 | B35: Colorado | C35: https://sbg.colorado.gov/sites/sbg/files/RR%20Services%20Final%2003142016_1_1.pdf | D35: Mandatory | E35: 42443ColoradoRR Services LLC | F35: RR Services LLC
A36: 42446 | B36: Colorado | C36: https://sbg.colorado.gov/sites/sbg/files/MGI%20HSA%2003172016_1_1.pdf | D36: Mandatory | E36: 42446ColoradoMGI Inc | F36: MGI Inc
A37: 42450 | B37: Colorado | C37: https://sbg.colorado.gov/sites/sbg/files/Colorados%20Best%2003212016_1.pdf | D37: Mandatory | E37: 42450ColoradoColorados Best Inc | F37: Colorados Best Inc
... A225: 45140 | B225: Washington | C225: https://lcb.wa.gov/marj/notice_of_recalls | D225: Mandatory | E225: 45140WashingtonOlympic Reef, LLC | F225: Olympic Reef, LLC

Sheet Batches
A1: Research ID | B1: Batch ID | C1: Medical Marijuana Center | D1: Medical Marijuana Cultivation License | E1: MM Manufacturer's | F1: Manufacturer's License | G1: Retail Marijuana Cultivation License | H1: Retail Store | I1: Retail Products Manufacturing
A2: CO424171 | B2: 2015-03-21-Drying Room-H | C2: 402-00242 | D2: 403-00365
A3: CO424171 | B3: 2015-05-08-Drying Room-H | C3: 402-00242 | D3: 403-00365
A4: CO424171 | B4: 2016-01-11-Drying Room-H | C4: 402-00242 | D4: 403-00365
A5: CO424171 | B5: 707-082615-8 | C5: 402-00242 | D5: 403-00365
A6: CO424171 | B6: 707HB-062815-5 | C6: 402-00242 | D6: 403-00365
A7: CO424171 | B7: 707HB-071315-10 | C7: 402-00242 | D7: 403-00365
A8: CO424171 | B8: 707HB-071315-10 | C8: 402-00242 | D8: 403-00365
A9: CO424171 | B9: 707HB-102315-6 | C9: 402-00242 | D9: 403-00365
A10: CO424171 | B10: 707HB-111815-1 | C10: 402-00242 | D10: 403-00365
A11: CO424171 | B11: 707HB-112915-1 | C11: 402-00242 | D11: 403-00365
A12: CO424171 | B12: 707HB-120815-1 | C12: 402-00242 | D12: 403-00365
A13: CO424171 | B13: AK48-071115-2 | C13: 402-00242 | D13: 403-00365
... A274: CO424171 | B274: Tangilope-100515-10 | C274: 402-00242 | D274: 403-00365
A275: CO424172 | B275: 012016 tanq1 | D275: 403-01366 | F275: 404-00352
A276: CO424172 | B276: 012016 tranq1 | D276: 403-01366 | F276: 404-00352
A277: CO424172 | B277: 012016 Tranq2 | D277: 403-01366 | F277: 404-00352
A278: CO424172 | B278: 1/25/16 Purple Dream (PD012516) | D278: 403-01366 | F278: 404-00352
A279: CO424172 | B279: 1/25/16 Ruskin Chronic (RC012516) | D279: 403-01366 | F279: 404-00352
A280: CO424172 | B280: 1/25/16 Shoreline #4 (S4012516) | D280: 403-01366 | F280: 404-00352
A281: CO424172 | B281: 1/25/16 Special Sour Diesel (SS012516) | D281: 403-01366 | F281: 404-00352
A282: CO424172 | B282: 1/25/16 Sugar Black Rose (SB012516) | D282: 403-01366 | F282: 404-00352
A283: CO424172 | B283: 1/26/16 Sugar Black Rose (SB012616) | D283: 403-01366 | F283: 404-00352
A284: CO424172 | B284: 1/26/2016 Shoreline #1 (S1012616) | D284: 403-01366 | F284: 404-00352
A285: CO424172 | B285: 1/28/16 Chem Dawg (CD012516) | D285: 403-01366 | F285: 404-00352
A286: CO424172 | B286: 1-26-15 Shoreline #3 (SH012615) | D286: 403-01366 | F286: 404-00352
... A319: CO424172 | B319: 8-5-15 Shoreline | D319: 403-01366 | F319: 404-00352
A320: CO424172 | B320: 1-29-16 Buddha's Sister (BS012916) | C320: 402-00875 | D320: 403-01367, 403-01571
A321: CO424172 | B321: 1-29-16 Chem Dawg (CD012916) | C321: 402-00875 | D321: 403-01367, 403-01571
A322: CO424172 | B322: 1/4/16 Grape Ape | C322: 402-00875 | D322: 403-01367, 403-01571
A323: CO424172 | B323: 1/4/16 NYCD Blast | C323: 402-00875 | D323: 403-01367, 403-01571
A324: CO424172 | B324: 10-28-15 OJ Blast | C324: 402-00875 | D324: 403-01367, 403-01571
A325: CO424172 | B325: 1-12-16 Grape Ape(R) | C325: 402-00875 | D325: 403-01367, 403-01571
A326: CO424172 | B326: 1-13-16 OJ | C326: 402-00875 | D326: 403-01367, 403-01571
A327: CO424172 | B327: 1-19-16 Shoreline #3 | C327: 402-00875 | D327: 403-01367, 403-01571
A328: CO424172 | B328: 12-22-15 AK-47 | C328: 402-00875 | D328: 403-01367, 403-01571
A329: CO424172 | B329: 12-22-15 Lost Coast OG | C329: 402-00875 | D329: 403-01367, 403-01571
A330: CO424172 | B330: 12-22-15 NYCD | C330: 402-00875 | D330: 403-01367, 403-01571
A331: CO424172 | B331: 12-23 & 24-15 AK-47 | C331: 402-00875 | D331: 403-01367, 403-01571
... A419: CO424172 | B419: Chiesel (TQAD) | C419: 402-01078 | D419: 403-01676
A420: CO424233 | B420: 2016-01-11-Harvest/Dry Room-H | G420: 403R-00160
A421: CO424244 | B421: 2016-02-12-GD | C421: 402-00251 | D421: 403-00375
A422: CO424244 | B422: 2016-02-12-GG | C422: 402-00251 | D422: 403-00375
A423: CO424244 | B423: 2016-02-12-CH | C423: 402-00251 | D423: 403-00375
A424: CO424244 | B424: 2016-02-12-DW | C424: 402-00251 | D424: 403-00375
A425: CO424244 | B425: 2016-02-12-DP | C425: 402-00251 | D425: 403-00375
A426: CO424244 | B426: 2016-02-12-DRY ROOM-H | C426: 402-00251 | D426: 403-00375
A427: CO424244 | B427: 2016-02-12-HB | C427: 402-00251 | D427: 403-00375
A428: CO424244 | B428: 2016-02-12-HG | C428: 402-00251 | D428: 403-00375
A429: CO424244 | B429: 2016-02-12-PG | C429: 402-00251 | D429: 403-00375
A430: CO424244 | B430: 2016-02-12-RE | C430: 402-00251 | D430: 403-00375
A431: CO424244 | B431: 2016-02-12-TP | C431: 402-00251 | D431: 403-00375
A432: CO424244 | B432: 2016-02-12-SZ | C432: 402-00251 | D432: 403-00375
... A588: CO424255 | B588: SS 9141 | C588: 402-00583 | D588: 403-00865
A589: CO424255 | B589: 01-0-16-GG 9880 | G589: 403R-00216
A590: CO424255 | B590: 01-04-16-BK 9171 | G590: 403R-00216
A591: CO424255 | B591: R0-2-8-16-BD 6359 | G591: 403R-00216
A592: CO424255 | B592: R0-2-8-16-BTG 9043 | G592: 403R-00216
A593: CO424255 | B593: R0-2-8-16-CD 6413 | G593: 403R-00216
A594: CO424255 | B594: R0-2-8-16-GA 5950 | G594: 403R-00216
A595: CO424255 | B595: R0-2-8-16-GC 9420 | G595: 403R-00216
A596: CO424255 | B596: R0-2-8-16-GD 4737 | G596: 403R-00216
A597: CO424255 | B597: R0-2-8-16-MB 1301 | G597: 403R-00216
A598: CO424255 | B598: R1-15-16-GG 3074 | G598: 403R-00216
A599: CO424255 | B599: R1-2-15-16-AK 1686 | G599: 403R-00216
A600: CO424255 | B600: R1-2-15-16-AK 2611 | G600: 403R-00216
... A789: CO424255 | B789: SOG-SD7235 | G789: 403R-00216
A790: CO424366 | B790: Holland's Hope 3-1 | C790: 402-00576 | D790: 403-00856
A791: CO424366 | B791: Eisbaer 3-1 | C791: 402-00576 | D791: 403-00856
A792: CO424366 | B792: UK Cheese 3-1 | C792: 402-00576 | D792: 403-00856
A793: CO424366 | B793: Kong 3-1 | C793: 402-00576 | D793: 403-00856
A794: CO424366 | B794: Appalachian Mud Squid 3-1 | C794: 402-00576 | D794: 403-00856
A795: CO424366 | B795: Hollands Hope 237 | C795: 402-00576 | D795: 403-00856
A796: CO424366 | B796: UK Cheese 228 | C796: 402-00576 | D796: 403-00856
A797: CO424366 | B797: Hollands Hope 239 | C797: 402-00576 | D797: 403-00856
A798: CO424366 | B798: Hollands Hope 235 | C798: 402-00576 | D798: 403-00856
A799: CO424366 | B799: Appalachian Mud Squid 220 | C799: 402-00576 | D799: 403-00856
A800: CO424366 | B800: Hollands Hope 234 | C800: 402-00576 | D800: 403-00856
A801: CO424366 | B801: Hollands Hope 238 | C801: 402-00576 | D801: 403-00856
... A850: CO424387 | B850: WSD 2/27/16 | C850: 402-00039 | D850: 403-00339
A851: CO424398 | B851: 1-11-16 Clusterfunk | G851: 403R-00445
A852: CO424398 | B852: 1-11-16 Black Bubba | G852: 403R-00445
A853: CO424398 | B853: 1-11-16 Cali Sunset | G853: 403R-00445
A854: CO424398 | B854: 1-11-16 LBK | G854: 403R-00445
A855: CO424398 | B855: 1-11-16 A-Dub | G855: 403R-00445
A856: CO424398 | B856: 1-11-16 Thunderf#ck | G856: 403R-00445
A857: CO424398 | B857: 1-11-16 Harlequin | G857: 403R-00445
A858: CO424398 | B858: 1-11-16 S.A.G.E. | G858: 403R-00445
A859: CO424398 | B859: 1-18-16 Cali Sunset | G859: 403R-00445
A860: CO424398 | B860: 1-25-16 Harlequin | G860: 403R-00445
A861: CO424398 | B861: 1-25-16 Juanita La Lagrimosa | G861: 403R-00445
A862: CO424398 | B862: 2-1-16 Purple Trainwreck | G862: 403R-00445
... A902: CO424399 | B902: 06-04-0044 Pesticide TEST | G902: 403R-00275
A903: CO4244310 | B903: Harvest 2/5/16 | C903: 402-00649 | D903: 403-00980
A904: CO4244310 | B904: 2-29 DAY ROOM #1 | C904: 402-00649 | D904: 403-01534
A905: CO4244310 | B905: 2-29 STAR DAWG ROOM #1 | C905: 402-00649 | D905: 403-01534
A906: CO4244310 | B906: 2-29 PINE EX ROOM #1 | C906: 402-00649 | D906: 403-01534
A907: CO4244310 | B907: 229 D-STAR ROOM#1- | C907: 402-00649 | D907: 403-01534
A908: CO4244310 | B908: 2-29 MOBB B ROOM#1 | C908: 402-00649 | D908: 403-01534
A909: CO4244310 | B909: 2-29 GRAPE ROOM #1 | C909: 402-00649 | D909: 403-01534
...
